<?xml version="1.0" encoding="utf-8" ?>
<DbtPaymentStatus xmlns="http://cpsms.nic.in/BeneficiaryPaymentStatus">
<CstmrCdtTrfInitn>
<GrpHdr>
<MsgId>
0026DBTPAYSTS060920175_00003</MsgId>
<CreDtTm>
06-09-2017 12:38:16 PM</CreDtTm>
<NbOfTxs>
16</NbOfTxs>
<CtrlSum>
739888.00</CtrlSum>
<Src>
0026</Src>
<Dest>
CPSMS</Dest>
<InitgPty>
<Nm>DIRECTORATE OF AGRICULTURE KHOD</Nm>
<PrTry>
<Id> ORKH00005622</Id>
</PrTry>
</InitgPty>
</GrpHdr>
<PmtInf>
<PmtInfId></PmtInfId>
<PmtInfDt>2017-12-09</PmtInfDt>
<PmtAuthCtre>
</PmtAuthCtre>
<PmtAuthPrvc>
</PmtAuthPrvc>
<OrgId>
<Cd>
ORKH00005622</Cd>
<Nm>
DIRECTORATE OF AGRICULTURE KHOD</Nm>
<SchmeCd>
2054</SchmeCd>
</OrgId>
<PmtMtd>
A</PmtMtd>
<BtchBookg>
true</BtchBookg>
<ReqdExctnDt>
2017-09-06</ReqdExctnDt>
<CdtTrfTxInf>
<PmtId>
<InstrId>N249170362874330</InstrId>
<EndToEndId>
Bhdn-Pow-0039/FID/2017-182054</EndToEndId>
</PmtId>
<Amt>
<CtreAmt>
0.00</CtreAmt>
<PrvcAmt>
15000.00</PrvcAmt>
<InstdAmt>
15000.00</InstdAmt>
</Amt>
<CdtrAgt>
<FinInstnId>
<BICFI>
STATE BANK OF INDIA</BICFI>
<BrnchId>
SBIN0003379</BrnchId>
</FinInstnId>
</CdtrAgt>
<Cdtr>
<PrTry>
<Id>
S10306040102</Id>
</PrTry>
<PFMSId>
BORKH02939317</PFMSId>
<Tp></Tp>
<Titl></Titl>
<Nm>
DIPAK KUMAR BHOI</Nm>
<PstlAdr>
<Prtry>
<DstCd>
03</DstCd>
<PrvcCd>
21</PrvcCd>
</Prtry>
</PstlAdr>
<CdtrAcct>
<Id>
<Othr>
<BBAN>
11710548017</BBAN>
<SOSE>
267100123098</SOSE>
</Othr>
</Id>
</CdtrAcct>
</Cdtr>
<TxSts>ACCP</TxSts>
<StsRsnInf>
<Rsn>
<Cd>  </Cd>
<AddtlInf></AddtlInf>
</Rsn>
</StsRsnInf>
<RltdInf>
<Rem>
Subsidy by DAFP.</Rem>
</RltdInf>
</CdtTrfTxInf>
<CdtTrfTxInf>
<PmtId>
<InstrId>N249170362869800</InstrId>
<EndToEndId>
Bhdn-Pow-0041/FID/2017-182054</EndToEndId>
</PmtId>
<Amt>
<CtreAmt>
0.00</CtreAmt>
<PrvcAmt>
15000.00</PrvcAmt>
<InstdAmt>
15000.00</InstdAmt>
</Amt>
<CdtrAgt>
<FinInstnId>
<BICFI>
STATE BANK OF INDIA</BICFI>
<BrnchId>
SBIN0009644</BrnchId>
</FinInstnId>
</CdtrAgt>
<Cdtr>
<PrTry>
<Id>
0517024352</Id>
</PrTry>
<PFMSId>
BORKH08346154</PFMSId>
<Tp></Tp>
<Titl></Titl>
<Nm>
SRINIBAS BHOI</Nm>
<PstlAdr>
<Prtry>
<DstCd>
03</DstCd>
<PrvcCd>
21</PrvcCd>
</Prtry>
</PstlAdr>
<CdtrAcct>
<Id>
<Othr>
<BBAN>
30878206078</BBAN>
<SOSE>
977472779638</SOSE>
</Othr>
</Id>
</CdtrAcct>
</Cdtr>
<TxSts>ACCP</TxSts>
<StsRsnInf>
<Rsn>
<Cd>  </Cd>
<AddtlInf></AddtlInf>
</Rsn>
</StsRsnInf>
<RltdInf>
<Rem>
Subsidy by DAFP.</Rem>
</RltdInf>
</CdtTrfTxInf>
<CdtTrfTxInf>
<PmtId>
<InstrId>N249170362855824</InstrId>
<EndToEndId>
Bhdn-Pow-0064/FID/2017-182054</EndToEndId>
</PmtId>
<Amt>
<CtreAmt>
0.00</CtreAmt>
<PrvcAmt>
15000.00</PrvcAmt>
<InstdAmt>
15000.00</InstdAmt>
</Amt>
<CdtrAgt>
<FinInstnId>
<BICFI>
STATE BANK OF INDIA</BICFI>
<BrnchId>
SBIN0003379</BrnchId>
</FinInstnId>
</CdtrAgt>
<Cdtr>
<PrTry>
<Id>
S10306041227</Id>
</PrTry>
<PFMSId>
BORKH03917697</PFMSId>
<Tp></Tp>
<Titl></Titl>
<Nm>
DAKHILA SAHU</Nm>
<PstlAdr>
<Prtry>
<DstCd>
03</DstCd>
<PrvcCd>
21</PrvcCd>
</Prtry>
</PstlAdr>
<CdtrAcct>
<Id>
<Othr>
<BBAN>
31437993332</BBAN>
<SOSE>
354191063727</SOSE>
</Othr>
</Id>
</CdtrAcct>
</Cdtr>
<TxSts>ACCP</TxSts>
<StsRsnInf>
<Rsn>
<Cd>  </Cd>
<AddtlInf></AddtlInf>
</Rsn>
</StsRsnInf>
<RltdInf>
<Rem>
Subsidy by DAFP.</Rem>
</RltdInf>
</CdtTrfTxInf>
<CdtTrfTxInf>
<PmtId>
<InstrId>N249170362855825</InstrId>
<EndToEndId>
Brgh-Pow-0037/FID/2017-182054</EndToEndId>
</PmtId>
<Amt>
<CtreAmt>
0.00</CtreAmt>
<PrvcAmt>
15000.00</PrvcAmt>
<InstdAmt>
15000.00</InstdAmt>
</Amt>
<CdtrAgt>
<FinInstnId>
<BICFI>
ANDHRA BANK</BICFI>
<BrnchId>
ANDB0000038</BrnchId>
</FinInstnId>
</CdtrAgt>
<Cdtr>
<PrTry>
<Id>
0617074173</Id>
</PrTry>
<PFMSId>
BORKH08830994</PFMSId>
<Tp></Tp>
<Titl></Titl>
<Nm>
MR PANCHANANDA SAHU</Nm>
<PstlAdr>
<Prtry>
<DstCd>
03</DstCd>
<PrvcCd>
21</PrvcCd>
</Prtry>
</PstlAdr>
<CdtrAcct>
<Id>
<Othr>
<BBAN>
003810100106198</BBAN>
<SOSE>
764822546783</SOSE>
</Othr>
</Id>
</CdtrAcct>
</Cdtr>
<TxSts>ACCP</TxSts>
<StsRsnInf>
<Rsn>
<Cd>  </Cd>
<AddtlInf></AddtlInf>
</Rsn>
</StsRsnInf>
<RltdInf>
<Rem>
Subsidy by DAFP.</Rem>
</RltdInf>
</CdtTrfTxInf>
<CdtTrfTxInf>
<PmtId>
<InstrId>N249170362855827</InstrId>
<EndToEndId>
Brpl-Pow-0029/FID/2017-182054</EndToEndId>
</PmtId>
<Amt>
<CtreAmt>
0.00</CtreAmt>
<PrvcAmt>
15000.00</PrvcAmt>
<InstdAmt>
15000.00</InstdAmt>
</Amt>
<CdtrAgt>
<FinInstnId>
<BICFI>
IDBI BANK LTD</BICFI>
<BrnchId>
IBKL0000746</BrnchId>
</FinInstnId>
</CdtrAgt>
<Cdtr>
<PrTry>
<Id>
S10304030611</Id>
</PrTry>
<PFMSId>
BORKH04330666</PFMSId>
<Tp></Tp>
<Titl></Titl>
<Nm>
RANJAN KUMAR SAHU</Nm>
<PstlAdr>
<Prtry>
<DstCd>
03</DstCd>
<PrvcCd>
21</PrvcCd>
</Prtry>
</PstlAdr>
<CdtrAcct>
<Id>
<Othr>
<BBAN>
746104000005579</BBAN>
<SOSE>
913141384748</SOSE>
</Othr>
</Id>
</CdtrAcct>
</Cdtr>
<TxSts>ACCP</TxSts>
<StsRsnInf>
<Rsn>
<Cd>  </Cd>
<AddtlInf></AddtlInf>
</Rsn>
</StsRsnInf>
<RltdInf>
<Rem>
Subsidy by DAFP.</Rem>
</RltdInf>
</CdtTrfTxInf>
<CdtTrfTxInf>
<PmtId>
<InstrId>N249170362869802</InstrId>
<EndToEndId>
Brpl-Pow-0030/FID/2017-182054</EndToEndId>
</PmtId>
<Amt>
<CtreAmt>
0.00</CtreAmt>
<PrvcAmt>
15000.00</PrvcAmt>
<InstdAmt>
15000.00</InstdAmt>
</Amt>
<CdtrAgt>
<FinInstnId>
<BICFI>
STATE BANK OF INDIA</BICFI>
<BrnchId>
SBIN0002012</BrnchId>
</FinInstnId>
</CdtrAgt>
<Cdtr>
<PrTry>
<Id>
S10304060025</Id>
</PrTry>
<PFMSId>
BORKH04378945</PFMSId>
<Tp></Tp>
<Titl></Titl>
<Nm>
SHANKAR BEHERA</Nm>
<PstlAdr>
<Prtry>
<DstCd>
03</DstCd>
<PrvcCd>
21</PrvcCd>
</Prtry>
</PstlAdr>
<CdtrAcct>
<Id>
<Othr>
<BBAN>
11280422929</BBAN>
<SOSE>
415106329437</SOSE>
</Othr>
</Id>
</CdtrAcct>
</Cdtr>
<TxSts>ACCP</TxSts>
<StsRsnInf>
<Rsn>
<Cd>  </Cd>
<AddtlInf></AddtlInf>
</Rsn>
</StsRsnInf>
<RltdInf>
<Rem>
Subsidy by DAFP.</Rem>
</RltdInf>
</CdtTrfTxInf>
<CdtTrfTxInf>
<PmtId>
<InstrId>N249170362874345</InstrId>
<EndToEndId>
Brpl-Pow-0031/FID/2017-182054</EndToEndId>
</PmtId>
<Amt>
<CtreAmt>
0.00</CtreAmt>
<PrvcAmt>
15000.00</PrvcAmt>
<InstdAmt>
15000.00</InstdAmt>
</Amt>
<CdtrAgt>
<FinInstnId>
<BICFI>
STATE BANK OF INDIA</BICFI>
<BrnchId>
SBIN0002012</BrnchId>
</FinInstnId>
</CdtrAgt>
<Cdtr>
<PrTry>
<Id>
S10304030049</Id>
</PrTry>
<PFMSId>
BORKH04214526</PFMSId>
<Tp></Tp>
<Titl></Titl>
<Nm>
SANJAY KUMAR SAHU</Nm>
<PstlAdr>
<Prtry>
<DstCd>
03</DstCd>
<PrvcCd>
21</PrvcCd>
</Prtry>
</PstlAdr>
<CdtrAcct>
<Id>
<Othr>
<BBAN>
11280433805</BBAN>
<SOSE>
378396421615</SOSE>
</Othr>
</Id>
</CdtrAcct>
</Cdtr>
<TxSts>ACCP</TxSts>
<StsRsnInf>
<Rsn>
<Cd>  </Cd>
<AddtlInf></AddtlInf>
</Rsn>
</StsRsnInf>
<RltdInf>
<Rem>
Subsidy by DAFP.</Rem>
</RltdInf>
</CdtTrfTxInf>
<CdtTrfTxInf>
<PmtId>
<InstrId>N249170362874348</InstrId>
<EndToEndId>
Jhar-Pow-0003/FID/2017-182054</EndToEndId>
</PmtId>
<Amt>
<CtreAmt>
0.00</CtreAmt>
<PrvcAmt>
75000.00</PrvcAmt>
<InstdAmt>
75000.00</InstdAmt>
</Amt>
<CdtrAgt>
<FinInstnId>
<BICFI>
STATE BANK OF INDIA</BICFI>
<BrnchId>
SBIN0000238</BrnchId>
</FinInstnId>
</CdtrAgt>
<Cdtr>
<PrTry>
<Id>
S11401010211</Id>
</PrTry>
<PFMSId>
BORKH04258045</PFMSId>
<Tp></Tp>
<Titl></Titl>
<Nm>
SURENDRA PATEL</Nm>
<PstlAdr>
<Prtry>
<DstCd>
14</DstCd>
<PrvcCd>
21</PrvcCd>
</Prtry>
</PstlAdr>
<CdtrAcct>
<Id>
<Othr>
<BBAN>
31103216185</BBAN>
<SOSE>
437679136405</SOSE>
</Othr>
</Id>
</CdtrAcct>
</Cdtr>
<TxSts>ACCP</TxSts>
<StsRsnInf>
<Rsn>
<Cd>  </Cd>
<AddtlInf></AddtlInf>
</Rsn>
</StsRsnInf>
<RltdInf>
<Rem>
Subsidy by DAFP.</Rem>
</RltdInf>
</CdtTrfTxInf>
<CdtTrfTxInf>
<PmtId>
<InstrId>N249170362855833</InstrId>
<EndToEndId>
Kola-Pow-0031/FID/2017-182054</EndToEndId>
</PmtId>
<Amt>
<CtreAmt>
0.00</CtreAmt>
<PrvcAmt>
15000.00</PrvcAmt>
<InstdAmt>
15000.00</InstdAmt>
</Amt>
<CdtrAgt>
<FinInstnId>
<BICFI>
CENTRAL BANK OF INDIA</BICFI>
<BrnchId>
CBIN0283309</BrnchId>
</FinInstnId>
</CdtrAgt>
<Cdtr>
<PrTry>
<Id>
0617033757</Id>
</PrTry>
<PFMSId>
BORKH08625024</PFMSId>
<Tp></Tp>
<Titl></Titl>
<Nm>
Shyam Sundar Singh</Nm>
<PstlAdr>
<Prtry>
<DstCd>
14</DstCd>
<PrvcCd>
21</PrvcCd>
</Prtry>
</PstlAdr>
<CdtrAcct>
<Id>
<Othr>
<BBAN>
3532918683</BBAN>
<SOSE>
549701637233</SOSE>
</Othr>
</Id>
</CdtrAcct>
</Cdtr>
<TxSts>ACCP</TxSts>
<StsRsnInf>
<Rsn>
<Cd>  </Cd>
<AddtlInf></AddtlInf>
</Rsn>
</StsRsnInf>
<RltdInf>
<Rem>
Subsidy by DAFP.</Rem>
</RltdInf>
</CdtTrfTxInf>
<CdtTrfTxInf>
<PmtId>
<InstrId>N249170362855834</InstrId>
<EndToEndId>
Krim-Spl-0001/FID/2017-182054</EndToEndId>
</PmtId>
<Amt>
<CtreAmt>
0.00</CtreAmt>
<PrvcAmt>
70000.00</PrvcAmt>
<InstdAmt>
70000.00</InstdAmt>
</Amt>
<CdtrAgt>
<FinInstnId>
<BICFI>
STATE BANK OF INDIA</BICFI>
<BrnchId>
SBIN0000238</BrnchId>
</FinInstnId>
</CdtrAgt>
<Cdtr>
<PrTry>
<Id>
0317007592</Id>
</PrTry>
<PFMSId>
BORKH07374717</PFMSId>
<Tp></Tp>
<Titl></Titl>
<Nm>
THANDARAM NAIK</Nm>
<PstlAdr>
<Prtry>
<DstCd>
14</DstCd>
<PrvcCd>
21</PrvcCd>
</Prtry>
</PstlAdr>
<CdtrAcct>
<Id>
<Othr>
<BBAN>
11346800220</BBAN>
<SOSE>
581560178635</SOSE>
</Othr>
</Id>
</CdtrAcct>
</Cdtr>
<TxSts>ACCP</TxSts>
<StsRsnInf>
<Rsn>
<Cd>  </Cd>
<AddtlInf></AddtlInf>
</Rsn>
</StsRsnInf>
<RltdInf>
<Rem>
Subsidy by DAFP.</Rem>
</RltdInf>
</CdtTrfTxInf>
<CdtTrfTxInf>
<PmtId>
<InstrId>N249170362855837</InstrId>
<EndToEndId>
Laik-Pow-0014/FID/2016-172054</EndToEndId>
</PmtId>
<Amt>
<CtreAmt>
0.00</CtreAmt>
<PrvcAmt>
75000.00</PrvcAmt>
<InstdAmt>
75000.00</InstdAmt>
</Amt>
<CdtrAgt>
<FinInstnId>
<BICFI>
PUNJAB NATIONAL BANK</BICFI>
<BrnchId>
PUNB0206200</BrnchId>
</FinInstnId>
</CdtrAgt>
<Cdtr>
<PrTry>
<Id>
S11404030841</Id>
</PrTry>
<PFMSId>
BORKH03982738</PFMSId>
<Tp></Tp>
<Titl></Titl>
<Nm>
SURAT PATEL</Nm>
<PstlAdr>
<Prtry>
<DstCd>
14</DstCd>
<PrvcCd>
21</PrvcCd>
</Prtry>
</PstlAdr>
<CdtrAcct>
<Id>
<Othr>
<BBAN>
2062001700078050</BBAN>
<SOSE>
810644388675</SOSE>
</Othr>
</Id>
</CdtrAcct>
</Cdtr>
<TxSts>ACCP</TxSts>
<StsRsnInf>
<Rsn>
<Cd>  </Cd>
<AddtlInf></AddtlInf>
</Rsn>
</StsRsnInf>
<RltdInf>
<Rem>
Subsidy by DAFP.</Rem>
</RltdInf>
</CdtTrfTxInf>
<CdtTrfTxInf>
<PmtId>
<InstrId>N249170362869811</InstrId>
<EndToEndId>
Laik-Pow-0015/FID/2016-172054</EndToEndId>
</PmtId>
<Amt>
<CtreAmt>
0.00</CtreAmt>
<PrvcAmt>
75000.00</PrvcAmt>
<InstdAmt>
75000.00</InstdAmt>
</Amt>
<CdtrAgt>
<FinInstnId>
<BICFI>
PUNJAB NATIONAL BANK</BICFI>
<BrnchId>
PUNB0206200</BrnchId>
</FinInstnId>
</CdtrAgt>
<Cdtr>
<PrTry>
<Id>
S11404010499</Id>
</PrTry>
<PFMSId>
BORKH04094167</PFMSId>
<Tp></Tp>
<Titl></Titl>
<Nm>
MADHAB CHARAN PATEL</Nm>
<PstlAdr>
<Prtry>
<DstCd>
14</DstCd>
<PrvcCd>
21</PrvcCd>
</Prtry>
</PstlAdr>
<CdtrAcct>
<Id>
<Othr>
<BBAN>
2062001700032243</BBAN>
<SOSE>
930680713015</SOSE>
</Othr>
</Id>
</CdtrAcct>
</Cdtr>
<TxSts>ACCP</TxSts>
<StsRsnInf>
<Rsn>
<Cd>  </Cd>
<AddtlInf></AddtlInf>
</Rsn>
</StsRsnInf>
<RltdInf>
<Rem>
Subsidy by DAFP.</Rem>
</RltdInf>
</CdtTrfTxInf>
<CdtTrfTxInf>
<PmtId>
<InstrId>N249170362869812</InstrId>
<EndToEndId>
DSMT-Pum-0002/FID/2017-182054</EndToEndId>
</PmtId>
<Amt>
<CtreAmt>
0.00</CtreAmt>
<PrvcAmt>
14888.00</PrvcAmt>
<InstdAmt>
14888.00</InstdAmt>
</Amt>
<CdtrAgt>
<FinInstnId>
<BICFI>
ANDHRA BANK</BICFI>
<BrnchId>
ANDB0001324</BrnchId>
</FinInstnId>
</CdtrAgt>
<Cdtr>
<PrTry>
<Id>
0717024667</Id>
</PrTry>
<PFMSId>
BORKH09134389</PFMSId>
<Tp></Tp>
<Titl></Titl>
<Nm>
BHAIRAB PRASAD GOUDA</Nm>
<PstlAdr>
<Prtry>
<DstCd>
20</DstCd>
<PrvcCd>
21</PrvcCd>
</Prtry>
</PstlAdr>
<CdtrAcct>
<Id>
<Othr>
<BBAN>
132410100142419</BBAN>
<SOSE>
200895268332</SOSE>
</Othr>
</Id>
</CdtrAcct>
</Cdtr>
<TxSts>ACCP</TxSts>
<StsRsnInf>
<Rsn>
<Cd>  </Cd>
<AddtlInf></AddtlInf>
</Rsn>
</StsRsnInf>
<RltdInf>
<Rem>
Subsidy by DAFP.</Rem>
</RltdInf>
</CdtTrfTxInf>
<CdtTrfTxInf>
<PmtId>
<InstrId>N249170362855839</InstrId>
<EndToEndId>
Dhnk-Trs-0012/FID/2017-182054</EndToEndId>
</PmtId>
<Amt>
<CtreAmt>
0.00</CtreAmt>
<PrvcAmt>
150000.00</PrvcAmt>
<InstdAmt>
150000.00</InstdAmt>
</Amt>
<CdtrAgt>
<FinInstnId>
<BICFI>
DENA BANK</BICFI>
<BrnchId>
BKDN0911638</BrnchId>
</FinInstnId>
</CdtrAgt>
<Cdtr>
<PrTry>
<Id>
S12802060070</Id>
</PrTry>
<PFMSId>
BORKH04381877</PFMSId>
<Tp></Tp>
<Titl></Titl>
<Nm>
OKIL MAHAPATRA</Nm>
<PstlAdr>
<Prtry>
<DstCd>
28</DstCd>
<PrvcCd>
21</PrvcCd>
</Prtry>
</PstlAdr>
<CdtrAcct>
<Id>
<Othr>
<BBAN>
163810032147</BBAN>
<SOSE>
748264900177</SOSE>
</Othr>
</Id>
</CdtrAcct>
</Cdtr>
<TxSts>ACCP</TxSts>
<StsRsnInf>
<Rsn>
<Cd>  </Cd>
<AddtlInf></AddtlInf>
</Rsn>
</StsRsnInf>
<RltdInf>
<Rem>
Subsidy by DAFP.</Rem>
</RltdInf>
</CdtTrfTxInf>
<CdtTrfTxInf>
<PmtId>
<InstrId>N249170362869818</InstrId>
<EndToEndId>
NUGN-Rot-0006/FID/2017-182054</EndToEndId>
</PmtId>
<Amt>
<CtreAmt>
0.00</CtreAmt>
<PrvcAmt>
80000.00</PrvcAmt>
<InstdAmt>
80000.00</InstdAmt>
</Amt>
<CdtrAgt>
<FinInstnId>
<BICFI>
STATE BANK OF INDIA</BICFI>
<BrnchId>
SBIN0007001</BrnchId>
</FinInstnId>
</CdtrAgt>
<Cdtr>
<PrTry>
<Id>
0616037561</Id>
</PrTry>
<PFMSId>
BORKH05044273</PFMSId>
<Tp></Tp>
<Titl></Titl>
<Nm>
BIRSA MUNDA</Nm>
<PstlAdr>
<Prtry>
<DstCd>
30</DstCd>
<PrvcCd>
21</PrvcCd>
</Prtry>
</PstlAdr>
<CdtrAcct>
<Id>
<Othr>
<BBAN>
31633230457</BBAN>
<SOSE>
752081255715</SOSE>
</Othr>
</Id>
</CdtrAcct>
</Cdtr>
<TxSts>ACCP</TxSts>
<StsRsnInf>
<Rsn>
<Cd>  </Cd>
<AddtlInf></AddtlInf>
</Rsn>
</StsRsnInf>
<RltdInf>
<Rem>
Subsidy by DAFP.</Rem>
</RltdInf>
</CdtTrfTxInf>
<CdtTrfTxInf>
<PmtId>
<InstrId>N249170362855844</InstrId>
<EndToEndId>
Sund-Rot-0005/FID/2017-182054</EndToEndId>
</PmtId>
<Amt>
<CtreAmt>
0.00</CtreAmt>
<PrvcAmt>
80000.00</PrvcAmt>
<InstdAmt>
80000.00</InstdAmt>
</Amt>
<CdtrAgt>
<FinInstnId>
<BICFI>
BANK OF INDIA</BICFI>
<BrnchId>
BKID0005207</BrnchId>
</FinInstnId>
</CdtrAgt>
<Cdtr>
<PrTry>
<Id>
0517035428</Id>
</PrTry>
<PFMSId>
BORKH08352761</PFMSId>
<Tp></Tp>
<Titl></Titl>
<Nm>
ABADHUTA SAHOO</Nm>
<PstlAdr>
<Prtry>
<DstCd>
30</DstCd>
<PrvcCd>
21</PrvcCd>
</Prtry>
</PstlAdr>
<CdtrAcct>
<Id>
<Othr>
<BBAN>
520710110007157</BBAN>
<SOSE>
222196499491</SOSE>
</Othr>
</Id>
</CdtrAcct>
</Cdtr>
<TxSts>ACCP</TxSts>
<StsRsnInf>
<Rsn>
<Cd>  </Cd>
<AddtlInf></AddtlInf>
</Rsn>
</StsRsnInf>
<RltdInf>
<Rem>
Subsidy by DAFP.</Rem>
</RltdInf>
</CdtTrfTxInf>
</PmtInf>
</CstmrCdtTrfInitn>
</DbtPaymentStatus>
