<DbtPaymentStatus xmlns="http://cpsms.nic.in/BeneficiaryPaymentStatus">
<CstmrCdtTrfInitn>
<GrpHdr>
<MsgId>0026DBTPAYSTS120720172_00004</MsgId>
<CreDtTm>13/07/2017 11:05:09 AM</CreDtTm>
<NbOfTxs>76</NbOfTxs>
<CtrlSum>7206250</CtrlSum>
<Src>PFMS</Src>
<Dest>0025</Dest>
<InitgPty>
<Nm>DIRECTORATE OF AGRICULTURE KHOD</Nm>
<PrTry>
<Id>ORKH00005622</Id>
</PrTry>
</InitgPty>
</GrpHdr>
<PmtInf>
<PmtInfId/>
<PmtInfDt>2017-13-07</PmtInfDt>
<PmtAuthCtre>
<Cd />
</PmtAuthCtre>
<PmtAuthPrvc>
<Cd />
</PmtAuthPrvc>
<OrgId>
<Cd>ORKH00005622</Cd>
<Nm>DIRECTORATE OF AGRICULTURE KHOD</Nm>
<SchmeCd>2054</SchmeCd>
</OrgId>
<CdtTrfTxInf>
<PmtId>
<InstrId> S9540036</InstrId>
<EndToEndId>AskaHPDTH0001SFIDS2017H182054</EndToEndId>
</PmtId>
<Amt>
<CtreAmt>0</CtreAmt>
<PrvcAmt>45000</PrvcAmt>
<InstdAmt>45000</InstdAmt>
</Amt>
<CdtrAgt>
<FinInstnId>
<BICFI>STATE BANK OF INDIA</BICFI>
<BrnchId>SBIN0000012</BrnchId>
</FinInstnId>
</CdtrAgt>
<Cdtr>
<PrTry>
<Id>2054</Id>
</PrTry>
<PFMSId>BORKH03104710</PFMSId>
<Tp/>
<Titl />
<Nm>BANAJABIHARI NAYAK</Nm>
<CdtrAcct>
<Id>
<Othr>
<BBAN>31322441510</BBAN>
<SOSE />
</Othr>
</Id>
</CdtrAcct>
</Cdtr>
<TxSts>ACCP</TxSts>
<StsRsnInf>
<Rsn>
<Cd/>
<AddtlInf/>
</Rsn>
</StsRsnInf>
<AddtlInfAPBS />
</CdtTrfTxInf>
<CdtTrfTxInf>
<PmtId>
<InstrId> S9540036</InstrId>
<EndToEndId>AtmkHRotH0001SFIDS2017H182054</EndToEndId>
</PmtId>
<Amt>
<CtreAmt>0</CtreAmt>
<PrvcAmt>79500</PrvcAmt>
<InstdAmt>79500</InstdAmt>
</Amt>
<CdtrAgt>
<FinInstnId>
<BICFI>INDIAN BANK</BICFI>
<BrnchId>IDIB000P142</BrnchId>
</FinInstnId>
</CdtrAgt>
<Cdtr>
<PrTry>
<Id>2054</Id>
</PrTry>
<PFMSId>BORKH04861515</PFMSId>
<Tp/>
<Titl />
<Nm>GHASIRAM MAHAKUD</Nm>
<CdtrAcct>
<Id>
<Othr>
<BBAN>6389301886</BBAN>
<SOSE />
</Othr>
</Id>
</CdtrAcct>
</Cdtr>
<TxSts>ACCP</TxSts>
<StsRsnInf>
<Rsn>
<Cd/>
<AddtlInf/>
</Rsn>
</StsRsnInf>
<AddtlInfAPBS />
</CdtTrfTxInf>
<CdtTrfTxInf>
<PmtId>
<InstrId> S9540036</InstrId>
<EndToEndId>BastHPowH0004SFIDS2017H182054</EndToEndId>
</PmtId>
<Amt>
<CtreAmt>0</CtreAmt>
<PrvcAmt>75000</PrvcAmt>
<InstdAmt>75000</InstdAmt>
</Amt>
<CdtrAgt>
<FinInstnId>
<BICFI>STATE BANK OF INDIA</BICFI>
<BrnchId>SBIN0009820</BrnchId>
</FinInstnId>
</CdtrAgt>
<Cdtr>
<PrTry>
<Id>2054</Id>
</PrTry>
<PFMSId>BORKH05339676</PFMSId>
<Tp/>
<Titl />
<Nm>RADHAMADHAB SINGHA</Nm>
<CdtrAcct>
<Id>
<Othr>
<BBAN>30885765083</BBAN>
<SOSE />
</Othr>
</Id>
</CdtrAcct>
</Cdtr>
<TxSts>ACCP</TxSts>
<StsRsnInf>
<Rsn>
<Cd/>
<AddtlInf/>
</Rsn>
</StsRsnInf>
<AddtlInfAPBS />
</CdtTrfTxInf>
<CdtTrfTxInf>
<PmtId>
<InstrId> S9540036</InstrId>
<EndToEndId>BastHRotH0002SFIDS2017H182054</EndToEndId>
</PmtId>
<Amt>
<CtreAmt>0</CtreAmt>
<PrvcAmt>80000</PrvcAmt>
<InstdAmt>80000</InstdAmt>
</Amt>
<CdtrAgt>
<FinInstnId>
<BICFI>BANK OF INDIA</BICFI>
<BrnchId>BKID0005482</BrnchId>
</FinInstnId>
</CdtrAgt>
<Cdtr>
<PrTry>
<Id>2054</Id>
</PrTry>
<PFMSId>BORKH04282041</PFMSId>
<Tp/>
<Titl />
<Nm>RANJAN KUMAR SAHU</Nm>
<CdtrAcct>
<Id>
<Othr>
<BBAN>548210110007357</BBAN>
<SOSE />
</Othr>
</Id>
</CdtrAcct>
</Cdtr>
<TxSts>ACCP</TxSts>
<StsRsnInf>
<Rsn>
<Cd/>
<AddtlInf/>
</Rsn>
</StsRsnInf>
<AddtlInfAPBS />
</CdtTrfTxInf>
<CdtTrfTxInf>
<PmtId>
<InstrId> S9540036</InstrId>
<EndToEndId>BbwrHRotH0002SFIDS2017H182054</EndToEndId>
</PmtId>
<Amt>
<CtreAmt>0</CtreAmt>
<PrvcAmt>80000</PrvcAmt>
<InstdAmt>80000</InstdAmt>
</Amt>
<CdtrAgt>
<FinInstnId>
<BICFI>STATE BANK OF INDIA</BICFI>
<BrnchId>SBIN0007187</BrnchId>
</FinInstnId>
</CdtrAgt>
<Cdtr>
<PrTry>
<Id>2054</Id>
</PrTry>
<PFMSId>BORKH08062277</PFMSId>
<Tp/>
<Titl />
<Nm>PRAMOD KUMAR PARIDA</Nm>
<CdtrAcct>
<Id>
<Othr>
<BBAN>30128823109</BBAN>
<SOSE />
</Othr>
</Id>
</CdtrAcct>
</Cdtr>
<TxSts>ACCP</TxSts>
<StsRsnInf>
<Rsn>
<Cd/>
<AddtlInf/>
</Rsn>
</StsRsnInf>
<AddtlInfAPBS />
</CdtTrfTxInf>
<CdtTrfTxInf>
<PmtId>
<InstrId> S9540036</InstrId>
<EndToEndId>BdsaHPowH0004SFIDS2017H182054</EndToEndId>
</PmtId>
<Amt>
<CtreAmt>0</CtreAmt>
<PrvcAmt>75000</PrvcAmt>
<InstdAmt>75000</InstdAmt>
</Amt>
<CdtrAgt>
<FinInstnId>
<BICFI>BANK OF INDIA</BICFI>
<BrnchId>BKID0005485</BrnchId>
</FinInstnId>
</CdtrAgt>
<Cdtr>
<PrTry>
<Id>2054</Id>
</PrTry>
<PFMSId>BORKH03733772</PFMSId>
<Tp/>
<Titl />
<Nm>MAMATA JENA</Nm>
<CdtrAcct>
<Id>
<Othr>
<BBAN>548510110002778</BBAN>
<SOSE />
</Othr>
</Id>
</CdtrAcct>
</Cdtr>
<TxSts>ACCP</TxSts>
<StsRsnInf>
<Rsn>
<Cd/>
<AddtlInf/>
</Rsn>
</StsRsnInf>
<AddtlInfAPBS />
</CdtTrfTxInf>
<CdtTrfTxInf>
<PmtId>
<InstrId> S9540036</InstrId>
<EndToEndId>BegnHPowH0003SFIDS2017H182054</EndToEndId>
</PmtId>
<Amt>
<CtreAmt>0</CtreAmt>
<PrvcAmt>75000</PrvcAmt>
<InstdAmt>75000</InstdAmt>
</Amt>
<CdtrAgt>
<FinInstnId>
<BICFI>STATE BANK OF INDIA</BICFI>
<BrnchId>SBIN0012027</BrnchId>
</FinInstnId>
</CdtrAgt>
<Cdtr>
<PrTry>
<Id>2054</Id>
</PrTry>
<PFMSId>BORKH08310403</PFMSId>
<Tp/>
<Titl />
<Nm>Jagadis prasad Das</Nm>
<CdtrAcct>
<Id>
<Othr>
<BBAN>30796190513</BBAN>
<SOSE />
</Othr>
</Id>
</CdtrAcct>
</Cdtr>
<TxSts>ACCP</TxSts>
<StsRsnInf>
<Rsn>
<Cd/>
<AddtlInf/>
</Rsn>
</StsRsnInf>
<AddtlInfAPBS />
</CdtTrfTxInf>
<CdtTrfTxInf>
<PmtId>
<InstrId> S9540036</InstrId>
<EndToEndId>BelhHSplH0002SFIDS2017H182054</EndToEndId>
</PmtId>
<Amt>
<CtreAmt>0</CtreAmt>
<PrvcAmt>70000</PrvcAmt>
<InstdAmt>70000</InstdAmt>
</Amt>
<CdtrAgt>
<FinInstnId>
<BICFI>BANK OF INDIA</BICFI>
<BrnchId>BKID0005153</BrnchId>
</FinInstnId>
</CdtrAgt>
<Cdtr>
<PrTry>
<Id>2054</Id>
</PrTry>
<PFMSId>BORKH03804890</PFMSId>
<Tp/>
<Titl />
<Nm>LAXMAN SAHU</Nm>
<CdtrAcct>
<Id>
<Othr>
<BBAN>515310100001576</BBAN>
<SOSE />
</Othr>
</Id>
</CdtrAcct>
</Cdtr>
<TxSts>ACCP</TxSts>
<StsRsnInf>
<Rsn>
<Cd/>
<AddtlInf/>
</Rsn>
</StsRsnInf>
<AddtlInfAPBS />
</CdtTrfTxInf>
<CdtTrfTxInf>
<PmtId>
<InstrId> S9540036</InstrId>
<EndToEndId>BelhHSplH0003SFIDS2016H172054</EndToEndId>
</PmtId>
<Amt>
<CtreAmt>0</CtreAmt>
<PrvcAmt>70000</PrvcAmt>
<InstdAmt>70000</InstdAmt>
</Amt>
<CdtrAgt>
<FinInstnId>
<BICFI>STATE BANK OF INDIA</BICFI>
<BrnchId>SBIN0013634</BrnchId>
</FinInstnId>
</CdtrAgt>
<Cdtr>
<PrTry>
<Id>2054</Id>
</PrTry>
<PFMSId>BORKH06305855</PFMSId>
<Tp/>
<Titl />
<Nm>RADHAKANTA SWAIN</Nm>
<CdtrAcct>
<Id>
<Othr>
<BBAN>31732420252</BBAN>
<SOSE />
</Othr>
</Id>
</CdtrAcct>
</Cdtr>
<TxSts>ACCP</TxSts>
<StsRsnInf>
<Rsn>
<Cd/>
<AddtlInf/>
</Rsn>
</StsRsnInf>
<AddtlInfAPBS />
</CdtTrfTxInf>
<CdtTrfTxInf>
<PmtId>
<InstrId> S9540036</InstrId>
<EndToEndId>BhogHPowH0003SFIDS2017H182054</EndToEndId>
</PmtId>
<Amt>
<CtreAmt>0</CtreAmt>
<PrvcAmt>75000</PrvcAmt>
<InstdAmt>75000</InstdAmt>
</Amt>
<CdtrAgt>
<FinInstnId>
<BICFI>UNITED BANK OF INDIA</BICFI>
<BrnchId>UTBI0BUD449</BrnchId>
</FinInstnId>
</CdtrAgt>
<Cdtr>
<PrTry>
<Id>2054</Id>
</PrTry>
<PFMSId>BORKH04208881</PFMSId>
<Tp/>
<Titl />
<Nm>AJIT RAJ</Nm>
<CdtrAcct>
<Id>
<Othr>
<BBAN>0523010359337</BBAN>
<SOSE />
</Othr>
</Id>
</CdtrAcct>
</Cdtr>
<TxSts>ACCP</TxSts>
<StsRsnInf>
<Rsn>
<Cd/>
<AddtlInf/>
</Rsn>
</StsRsnInf>
<AddtlInfAPBS />
</CdtTrfTxInf>
<CdtTrfTxInf>
<PmtId>
<InstrId> S9540036</InstrId>
<EndToEndId>BhogHPowH0005SFIDS2017H182054</EndToEndId>
</PmtId>
<Amt>
<CtreAmt>0</CtreAmt>
<PrvcAmt>75000</PrvcAmt>
<InstdAmt>75000</InstdAmt>
</Amt>
<CdtrAgt>
<FinInstnId>
<BICFI>UCO BANK</BICFI>
<BrnchId>UCBA0001111</BrnchId>
</FinInstnId>
</CdtrAgt>
<Cdtr>
<PrTry>
<Id>2054</Id>
</PrTry>
<PFMSId>BORKH03965345</PFMSId>
<Tp/>
<Titl />
<Nm>MURALI MOHAN JENA</Nm>
<CdtrAcct>
<Id>
<Othr>
<BBAN>11110100015858</BBAN>
<SOSE />
</Othr>
</Id>
</CdtrAcct>
</Cdtr>
<TxSts>ACCP</TxSts>
<StsRsnInf>
<Rsn>
<Cd/>
<AddtlInf/>
</Rsn>
</StsRsnInf>
<AddtlInfAPBS />
</CdtTrfTxInf>
<CdtTrfTxInf>
<PmtId>
<InstrId> S9540036</InstrId>
<EndToEndId>BhogHRotH0006SFIDS2017H182054</EndToEndId>
</PmtId>
<Amt>
<CtreAmt>0</CtreAmt>
<PrvcAmt>80000</PrvcAmt>
<InstdAmt>80000</InstdAmt>
</Amt>
<CdtrAgt>
<FinInstnId>
<BICFI>STATE BANK OF INDIA</BICFI>
<BrnchId>SBIN0010902</BrnchId>
</FinInstnId>
</CdtrAgt>
<Cdtr>
<PrTry>
<Id>2054</Id>
</PrTry>
<PFMSId>BORKH06057787</PFMSId>
<Tp/>
<Titl />
<Nm>PUSPANJALI JENA</Nm>
<CdtrAcct>
<Id>
<Othr>
<BBAN>33713555278</BBAN>
<SOSE />
</Othr>
</Id>
</CdtrAcct>
</Cdtr>
<TxSts>ACCP</TxSts>
<StsRsnInf>
<Rsn>
<Cd/>
<AddtlInf/>
</Rsn>
</StsRsnInf>
<AddtlInfAPBS />
</CdtTrfTxInf>
<CdtTrfTxInf>
<PmtId>
<InstrId> S9540036</InstrId>
<EndToEndId>BhogHRotH0009SFIDS2017H182054</EndToEndId>
</PmtId>
<Amt>
<CtreAmt>0</CtreAmt>
<PrvcAmt>80000</PrvcAmt>
<InstdAmt>80000</InstdAmt>
</Amt>
<CdtrAgt>
<FinInstnId>
<BICFI>PUNJAB NATIONAL BANK</BICFI>
<BrnchId>PUNB0728700</BrnchId>
</FinInstnId>
</CdtrAgt>
<Cdtr>
<PrTry>
<Id>2054</Id>
</PrTry>
<PFMSId>BORKH05230215</PFMSId>
<Tp/>
<Titl />
<Nm>SURENDRA NATH GANGAI</Nm>
<CdtrAcct>
<Id>
<Othr>
<BBAN>7287001100000118</BBAN>
<SOSE />
</Othr>
</Id>
</CdtrAcct>
</Cdtr>
<TxSts>ACCP</TxSts>
<StsRsnInf>
<Rsn>
<Cd/>
<AddtlInf/>
</Rsn>
</StsRsnInf>
<AddtlInfAPBS />
</CdtTrfTxInf>
<CdtTrfTxInf>
<PmtId>
<InstrId> S9540036</InstrId>
<EndToEndId>BktiHComH0006SFIDS2017H182054</EndToEndId>
</PmtId>
<Amt>
<CtreAmt>0</CtreAmt>
<PrvcAmt>600000</PrvcAmt>
<InstdAmt>600000</InstdAmt>
</Amt>
<CdtrAgt>
<FinInstnId>
<BICFI>INDIAN BANK</BICFI>
<BrnchId>IDIB000P170</BrnchId>
</FinInstnId>
</CdtrAgt>
<Cdtr>
<PrTry>
<Id>2054</Id>
</PrTry>
<PFMSId>BORKH07241573</PFMSId>
<Tp/>
<Titl />
<Nm>ARABINDA PARIDA</Nm>
<CdtrAcct>
<Id>
<Othr>
<BBAN>6026942745</BBAN>
<SOSE />
</Othr>
</Id>
</CdtrAcct>
</Cdtr>
<TxSts>ACCP</TxSts>
<StsRsnInf>
<Rsn>
<Cd/>
<AddtlInf/>
</Rsn>
</StsRsnInf>
<AddtlInfAPBS />
</CdtTrfTxInf>
<CdtTrfTxInf>
<PmtId>
<InstrId> S9540036</InstrId>
<EndToEndId>BktiHRotH0003SFIDS2017H182054</EndToEndId>
</PmtId>
<Amt>
<CtreAmt>0</CtreAmt>
<PrvcAmt>80000</PrvcAmt>
<InstdAmt>80000</InstdAmt>
</Amt>
<CdtrAgt>
<FinInstnId>
<BICFI>UCO BANK</BICFI>
<BrnchId>UCBA0001098</BrnchId>
</FinInstnId>
</CdtrAgt>
<Cdtr>
<PrTry>
<Id>2054</Id>
</PrTry>
<PFMSId>BORKH04416023</PFMSId>
<Tp/>
<Titl />
<Nm>BAURIBANDHU PRADHAN</Nm>
<CdtrAcct>
<Id>
<Othr>
<BBAN>10980100003958</BBAN>
<SOSE />
</Othr>
</Id>
</CdtrAcct>
</Cdtr>
<TxSts>ACCP</TxSts>
<StsRsnInf>
<Rsn>
<Cd/>
<AddtlInf/>
</Rsn>
</StsRsnInf>
<AddtlInfAPBS />
</CdtTrfTxInf>
<CdtTrfTxInf>
<PmtId>
<InstrId> S9540036</InstrId>
<EndToEndId>BlkdHRotH0011SFIDS2017H182054</EndToEndId>
</PmtId>
<Amt>
<CtreAmt>0</CtreAmt>
<PrvcAmt>80000</PrvcAmt>
<InstdAmt>80000</InstdAmt>
</Amt>
<CdtrAgt>
<FinInstnId>
<BICFI>STATE BANK OF INDIA</BICFI>
<BrnchId>SBIN0010915</BrnchId>
</FinInstnId>
</CdtrAgt>
<Cdtr>
<PrTry>
<Id>2054</Id>
</PrTry>
<PFMSId>BORKH08346416</PFMSId>
<Tp/>
<Titl />
<Nm>DEBASIS GIRI</Nm>
<CdtrAcct>
<Id>
<Othr>
<BBAN>32087026168</BBAN>
<SOSE />
</Othr>
</Id>
</CdtrAcct>
</Cdtr>
<TxSts>ACCP</TxSts>
<StsRsnInf>
<Rsn>
<Cd/>
<AddtlInf/>
</Rsn>
</StsRsnInf>
<AddtlInfAPBS />
</CdtTrfTxInf>
<CdtTrfTxInf>
<PmtId>
<InstrId> S9540036</InstrId>
<EndToEndId>BnslHPowH0001SFIDS2017H182054</EndToEndId>
</PmtId>
<Amt>
<CtreAmt>0</CtreAmt>
<PrvcAmt>75000</PrvcAmt>
<InstdAmt>75000</InstdAmt>
</Amt>
<CdtrAgt>
<FinInstnId>
<BICFI>BANK OF INDIA</BICFI>
<BrnchId>BKID0005413</BrnchId>
</FinInstnId>
</CdtrAgt>
<Cdtr>
<PrTry>
<Id>2054</Id>
</PrTry>
<PFMSId>BORKH07440627</PFMSId>
<Tp/>
<Titl />
<Nm>SRIDHAR MUNDA</Nm>
<CdtrAcct>
<Id>
<Othr>
<BBAN>541310110005063</BBAN>
<SOSE />
</Othr>
</Id>
</CdtrAcct>
</Cdtr>
<TxSts>ACCP</TxSts>
<StsRsnInf>
<Rsn>
<Cd/>
<AddtlInf/>
</Rsn>
</StsRsnInf>
<AddtlInfAPBS />
</CdtTrfTxInf>
<CdtTrfTxInf>
<PmtId>
<InstrId> S9540036</InstrId>
<EndToEndId>BnthHPowH0001SFIDS2017H182054</EndToEndId>
</PmtId>
<Amt>
<CtreAmt>0</CtreAmt>
<PrvcAmt>75000</PrvcAmt>
<InstdAmt>75000</InstdAmt>
</Amt>
<CdtrAgt>
<FinInstnId>
<BICFI>STATE BANK OF INDIA</BICFI>
<BrnchId>SBIN0006416</BrnchId>
</FinInstnId>
</CdtrAgt>
<Cdtr>
<PrTry>
<Id>2054</Id>
</PrTry>
<PFMSId>BORKH03368311</PFMSId>
<Tp/>
<Titl />
<Nm>KAILASH CHJENA</Nm>
<CdtrAcct>
<Id>
<Othr>
<BBAN>31052712916</BBAN>
<SOSE />
</Othr>
</Id>
</CdtrAcct>
</Cdtr>
<TxSts>ACCP</TxSts>
<StsRsnInf>
<Rsn>
<Cd/>
<AddtlInf/>
</Rsn>
</StsRsnInf>
<AddtlInfAPBS />
</CdtTrfTxInf>
<CdtTrfTxInf>
<PmtId>
<InstrId> S9540036</InstrId>
<EndToEndId>BpurHPowH0001SFIDS2017H182054</EndToEndId>
</PmtId>
<Amt>
<CtreAmt>0</CtreAmt>
<PrvcAmt>75000</PrvcAmt>
<InstdAmt>75000</InstdAmt>
</Amt>
<CdtrAgt>
<FinInstnId>
<BICFI>PUNJAB NATIONAL BANK</BICFI>
<BrnchId>PUNB0225500</BrnchId>
</FinInstnId>
</CdtrAgt>
<Cdtr>
<PrTry>
<Id>2054</Id>
</PrTry>
<PFMSId>BORKH04367497</PFMSId>
<Tp/>
<Titl />
<Nm>BALARAM PALAI</Nm>
<CdtrAcct>
<Id>
<Othr>
<BBAN>2255000100113996</BBAN>
<SOSE />
</Othr>
</Id>
</CdtrAcct>
</Cdtr>
<TxSts>ACCP</TxSts>
<StsRsnInf>
<Rsn>
<Cd/>
<AddtlInf/>
</Rsn>
</StsRsnInf>
<AddtlInfAPBS />
</CdtTrfTxInf>
<CdtTrfTxInf>
<PmtId>
<InstrId> S9540036</InstrId>
<EndToEndId>BpurHPowH0003SFIDS2017H182054</EndToEndId>
</PmtId>
<Amt>
<CtreAmt>0</CtreAmt>
<PrvcAmt>75000</PrvcAmt>
<InstdAmt>75000</InstdAmt>
</Amt>
<CdtrAgt>
<FinInstnId>
<BICFI>UCO BANK</BICFI>
<BrnchId>UCBA0000427</BrnchId>
</FinInstnId>
</CdtrAgt>
<Cdtr>
<PrTry>
<Id>2054</Id>
</PrTry>
<PFMSId>BORKH07964919</PFMSId>
<Tp/>
<Titl />
<Nm>Jogendra Behera</Nm>
<CdtrAcct>
<Id>
<Othr>
<BBAN>04270110100202</BBAN>
<SOSE />
</Othr>
</Id>
</CdtrAcct>
</Cdtr>
<TxSts>ACCP</TxSts>
<StsRsnInf>
<Rsn>
<Cd/>
<AddtlInf/>
</Rsn>
</StsRsnInf>
<AddtlInfAPBS />
</CdtTrfTxInf>
<CdtTrfTxInf>
<PmtId>
<InstrId> S9540036</InstrId>
<EndToEndId>BrdiHRotH0002SFIDS2017H182054</EndToEndId>
</PmtId>
<Amt>
<CtreAmt>0</CtreAmt>
<PrvcAmt>80000</PrvcAmt>
<InstdAmt>80000</InstdAmt>
</Amt>
<CdtrAgt>
<FinInstnId>
<BICFI>ODISHA GRAMYA BANK</BICFI>
<BrnchId>IOBA0ROGB01</BrnchId>
</FinInstnId>
</CdtrAgt>
<Cdtr>
<PrTry>
<Id>2054</Id>
</PrTry>
<PFMSId>BORKH05414328</PFMSId>
<Tp/>
<Titl />
<Nm>RAMANI RANJAN SAHOO</Nm>
<CdtrAcct>
<Id>
<Othr>
<BBAN>40820110008273</BBAN>
<SOSE />
</Othr>
</Id>
</CdtrAcct>
</Cdtr>
<TxSts>ACCP</TxSts>
<StsRsnInf>
<Rsn>
<Cd/>
<AddtlInf/>
</Rsn>
</StsRsnInf>
<AddtlInfAPBS />
</CdtTrfTxInf>
<CdtTrfTxInf>
<PmtId>
<InstrId> S9540036</InstrId>
<EndToEndId>BrdiHRotH0003SFIDS2017H182054</EndToEndId>
</PmtId>
<Amt>
<CtreAmt>0</CtreAmt>
<PrvcAmt>80000</PrvcAmt>
<InstdAmt>80000</InstdAmt>
</Amt>
<CdtrAgt>
<FinInstnId>
<BICFI>CANARA BANK</BICFI>
<BrnchId>CNRB0001750</BrnchId>
</FinInstnId>
</CdtrAgt>
<Cdtr>
<PrTry>
<Id>2054</Id>
</PrTry>
<PFMSId>BORKH07960516</PFMSId>
<Tp/>
<Titl />
<Nm>SANJUKTA BARIK</Nm>
<CdtrAcct>
<Id>
<Othr>
<BBAN>1750108016694</BBAN>
<SOSE />
</Othr>
</Id>
</CdtrAcct>
</Cdtr>
<TxSts>ACCP</TxSts>
<StsRsnInf>
<Rsn>
<Cd/>
<AddtlInf/>
</Rsn>
</StsRsnInf>
<AddtlInfAPBS />
</CdtTrfTxInf>
<CdtTrfTxInf>
<PmtId>
<InstrId> S9540036</InstrId>
<EndToEndId>BrdiHRotH0004SFIDS2017H182054</EndToEndId>
</PmtId>
<Amt>
<CtreAmt>0</CtreAmt>
<PrvcAmt>80000</PrvcAmt>
<InstdAmt>80000</InstdAmt>
</Amt>
<CdtrAgt>
<FinInstnId>
<BICFI>INDIAN BANK</BICFI>
<BrnchId>IDIB000B040</BrnchId>
</FinInstnId>
</CdtrAgt>
<Cdtr>
<PrTry>
<Id>2054</Id>
</PrTry>
<PFMSId>BORKH07960324</PFMSId>
<Tp/>
<Titl />
<Nm>MITANJALI SETHY</Nm>
<CdtrAcct>
<Id>
<Othr>
<BBAN>6140213255</BBAN>
<SOSE />
</Othr>
</Id>
</CdtrAcct>
</Cdtr>
<TxSts>ACCP</TxSts>
<StsRsnInf>
<Rsn>
<Cd/>
<AddtlInf/>
</Rsn>
</StsRsnInf>
<AddtlInfAPBS />
</CdtTrfTxInf>
<CdtTrfTxInf>
<PmtId>
<InstrId> S9540036</InstrId>
<EndToEndId>BRNGHRotH0002SFIDS2017H182054</EndToEndId>
</PmtId>
<Amt>
<CtreAmt>0</CtreAmt>
<PrvcAmt>80000</PrvcAmt>
<InstdAmt>80000</InstdAmt>
</Amt>
<CdtrAgt>
<FinInstnId>
<BICFI>ODISHA GRAMYA BANK</BICFI>
<BrnchId>IOBA0ROGB01</BrnchId>
</FinInstnId>
</CdtrAgt>
<Cdtr>
<PrTry>
<Id>2054</Id>
</PrTry>
<PFMSId>BORKH03755015</PFMSId>
<Tp/>
<Titl />
<Nm>SURJYANARAYAN DASH</Nm>
<CdtrAcct>
<Id>
<Othr>
<BBAN>40920100000166</BBAN>
<SOSE />
</Othr>
</Id>
</CdtrAcct>
</Cdtr>
<TxSts>ACCP</TxSts>
<StsRsnInf>
<Rsn>
<Cd/>
<AddtlInf/>
</Rsn>
</StsRsnInf>
<AddtlInfAPBS />
</CdtTrfTxInf>
<CdtTrfTxInf>
<PmtId>
<InstrId> S9540036</InstrId>
<EndToEndId>CHBLHPowH0013SFIDS2017H182054</EndToEndId>
</PmtId>
<Amt>
<CtreAmt>0</CtreAmt>
<PrvcAmt>75000</PrvcAmt>
<InstdAmt>75000</InstdAmt>
</Amt>
<CdtrAgt>
<FinInstnId>
<BICFI>UCO BANK</BICFI>
<BrnchId>UCBA0001361</BrnchId>
</FinInstnId>
</CdtrAgt>
<Cdtr>
<PrTry>
<Id>2054</Id>
</PrTry>
<PFMSId>BORKH08320687</PFMSId>
<Tp/>
<Titl />
<Nm>ANANTA KUMAR NAYAK</Nm>
<CdtrAcct>
<Id>
<Othr>
<BBAN>13610100002618</BBAN>
<SOSE />
</Othr>
</Id>
</CdtrAcct>
</Cdtr>
<TxSts>ACCP</TxSts>
<StsRsnInf>
<Rsn>
<Cd/>
<AddtlInf/>
</Rsn>
</StsRsnInf>
<AddtlInfAPBS />
</CdtTrfTxInf>
<CdtTrfTxInf>
<PmtId>
<InstrId> S9540036</InstrId>
<EndToEndId>CHKTHRotH0004SFIDS2017H182054</EndToEndId>
</PmtId>
<Amt>
<CtreAmt>0</CtreAmt>
<PrvcAmt>80000</PrvcAmt>
<InstdAmt>80000</InstdAmt>
</Amt>
<CdtrAgt>
<FinInstnId>
<BICFI>STATE BANK OF INDIA</BICFI>
<BrnchId>SBIN0010912</BrnchId>
</FinInstnId>
</CdtrAgt>
<Cdtr>
<PrTry>
<Id>2054</Id>
</PrTry>
<PFMSId>BORKH05044205</PFMSId>
<Tp/>
<Titl />
<Nm>GOPALA PANDA</Nm>
<CdtrAcct>
<Id>
<Othr>
<BBAN>30519324004</BBAN>
<SOSE />
</Othr>
</Id>
</CdtrAcct>
</Cdtr>
<TxSts>ACCP</TxSts>
<StsRsnInf>
<Rsn>
<Cd/>
<AddtlInf/>
</Rsn>
</StsRsnInf>
<AddtlInfAPBS />
</CdtTrfTxInf>
<CdtTrfTxInf>
<PmtId>
<InstrId> S9540036</InstrId>
<EndToEndId>CHKTHRotH0006SFIDS2017H182054</EndToEndId>
</PmtId>
<Amt>
<CtreAmt>0</CtreAmt>
<PrvcAmt>80000</PrvcAmt>
<InstdAmt>80000</InstdAmt>
</Amt>
<CdtrAgt>
<FinInstnId>
<BICFI>ANDHRA BANK</BICFI>
<BrnchId>ANDB0000992</BrnchId>
</FinInstnId>
</CdtrAgt>
<Cdtr>
<PrTry>
<Id>2054</Id>
</PrTry>
<PFMSId>BORKH05060260</PFMSId>
<Tp/>
<Titl />
<Nm>PRATAP KUMAR PADHY</Nm>
<CdtrAcct>
<Id>
<Othr>
<BBAN>099210021000903</BBAN>
<SOSE />
</Othr>
</Id>
</CdtrAcct>
</Cdtr>
<TxSts>ACCP</TxSts>
<StsRsnInf>
<Rsn>
<Cd/>
<AddtlInf/>
</Rsn>
</StsRsnInf>
<AddtlInfAPBS />
</CdtTrfTxInf>
<CdtTrfTxInf>
<PmtId>
<InstrId> S9540036</InstrId>
<EndToEndId>CHKTHRotH0007SFIDS2017H182054</EndToEndId>
</PmtId>
<Amt>
<CtreAmt>0</CtreAmt>
<PrvcAmt>80000</PrvcAmt>
<InstdAmt>80000</InstdAmt>
</Amt>
<CdtrAgt>
<FinInstnId>
<BICFI>STATE BANK OF INDIA</BICFI>
<BrnchId>SBIN0010912</BrnchId>
</FinInstnId>
</CdtrAgt>
<Cdtr>
<PrTry>
<Id>2054</Id>
</PrTry>
<PFMSId>BORKH08150373</PFMSId>
<Tp/>
<Titl />
<Nm>J.BISWANATH KANYARI</Nm>
<CdtrAcct>
<Id>
<Othr>
<BBAN>31728812417</BBAN>
<SOSE />
</Othr>
</Id>
</CdtrAcct>
</Cdtr>
<TxSts>ACCP</TxSts>
<StsRsnInf>
<Rsn>
<Cd/>
<AddtlInf/>
</Rsn>
</StsRsnInf>
<AddtlInfAPBS />
</CdtTrfTxInf>
<CdtTrfTxInf>
<PmtId>
<InstrId> S9540036</InstrId>
<EndToEndId>CHKTHRotH0008SFIDS2017H182054</EndToEndId>
</PmtId>
<Amt>
<CtreAmt>0</CtreAmt>
<PrvcAmt>80000</PrvcAmt>
<InstdAmt>80000</InstdAmt>
</Amt>
<CdtrAgt>
<FinInstnId>
<BICFI>INDIAN OVERSEAS BANK</BICFI>
<BrnchId>IOBA0000734</BrnchId>
</FinInstnId>
</CdtrAgt>
<Cdtr>
<PrTry>
<Id>2054</Id>
</PrTry>
<PFMSId>BORKH04404971</PFMSId>
<Tp/>
<Titl />
<Nm>GOUDA SETHI</Nm>
<CdtrAcct>
<Id>
<Othr>
<BBAN>073401000061033</BBAN>
<SOSE />
</Othr>
</Id>
</CdtrAcct>
</Cdtr>
<TxSts>ACCP</TxSts>
<StsRsnInf>
<Rsn>
<Cd/>
<AddtlInf/>
</Rsn>
</StsRsnInf>
<AddtlInfAPBS />
</CdtTrfTxInf>
<CdtTrfTxInf>
<PmtId>
<InstrId> S9540036</InstrId>
<EndToEndId>ChmaHPowH0017SFIDS2017H182054</EndToEndId>
</PmtId>
<Amt>
<CtreAmt>0</CtreAmt>
<PrvcAmt>75000</PrvcAmt>
<InstdAmt>75000</InstdAmt>
</Amt>
<CdtrAgt>
<FinInstnId>
<BICFI>ODISHA GRAMYA BANK</BICFI>
<BrnchId>IOBA0ROGB01</BrnchId>
</FinInstnId>
</CdtrAgt>
<Cdtr>
<PrTry>
<Id>2054</Id>
</PrTry>
<PFMSId>BORKH08119589</PFMSId>
<Tp/>
<Titl />
<Nm>SHANTANU SETHI </Nm>
<CdtrAcct>
<Id>
<Othr>
<BBAN>202610400003942</BBAN>
<SOSE />
</Othr>
</Id>
</CdtrAcct>
</Cdtr>
<TxSts>ACCP</TxSts>
<StsRsnInf>
<Rsn>
<Cd/>
<AddtlInf/>
</Rsn>
</StsRsnInf>
<AddtlInfAPBS />
</CdtTrfTxInf>
<CdtTrfTxInf>
<PmtId>
<InstrId> S9540036</InstrId>
<EndToEndId>CtckHRotH0003SFIDS2017H182054</EndToEndId>
</PmtId>
<Amt>
<CtreAmt>0</CtreAmt>
<PrvcAmt>80000</PrvcAmt>
<InstdAmt>80000</InstdAmt>
</Amt>
<CdtrAgt>
<FinInstnId>
<BICFI>INDIAN BANK</BICFI>
<BrnchId>IDIB000S094</BrnchId>
</FinInstnId>
</CdtrAgt>
<Cdtr>
<PrTry>
<Id>2054</Id>
</PrTry>
<PFMSId>BORKH07245586</PFMSId>
<Tp/>
<Titl />
<Nm>SHAKE ZABED ALI</Nm>
<CdtrAcct>
<Id>
<Othr>
<BBAN>6093272417</BBAN>
<SOSE />
</Othr>
</Id>
</CdtrAcct>
</Cdtr>
<TxSts>ACCP</TxSts>
<StsRsnInf>
<Rsn>
<Cd/>
<AddtlInf/>
</Rsn>
</StsRsnInf>
<AddtlInfAPBS />
</CdtTrfTxInf>
<CdtTrfTxInf>
<PmtId>
<InstrId> S9540036</InstrId>
<EndToEndId>CtckHRotH0004SFIDS2017H182054</EndToEndId>
</PmtId>
<Amt>
<CtreAmt>0</CtreAmt>
<PrvcAmt>80000</PrvcAmt>
<InstdAmt>80000</InstdAmt>
</Amt>
<CdtrAgt>
<FinInstnId>
<BICFI>STATE BANK OF INDIA</BICFI>
<BrnchId>SBIN0004229</BrnchId>
</FinInstnId>
</CdtrAgt>
<Cdtr>
<PrTry>
<Id>2054</Id>
</PrTry>
<PFMSId>BORKH04124659</PFMSId>
<Tp/>
<Titl />
<Nm>DIPANKAR SAHOO</Nm>
<CdtrAcct>
<Id>
<Othr>
<BBAN>10134235710</BBAN>
<SOSE />
</Othr>
</Id>
</CdtrAcct>
</Cdtr>
<TxSts>ACCP</TxSts>
<StsRsnInf>
<Rsn>
<Cd/>
<AddtlInf/>
</Rsn>
</StsRsnInf>
<AddtlInfAPBS />
</CdtTrfTxInf>
<CdtTrfTxInf>
<PmtId>
<InstrId> S9540036</InstrId>
<EndToEndId>DIGPHPumH0004SFIDS2017H182054</EndToEndId>
</PmtId>
<Amt>
<CtreAmt>0</CtreAmt>
<PrvcAmt>15000</PrvcAmt>
<InstdAmt>15000</InstdAmt>
</Amt>
<CdtrAgt>
<FinInstnId>
<BICFI>STATE BANK OF INDIA</BICFI>
<BrnchId>SBIN0010911</BrnchId>
</FinInstnId>
</CdtrAgt>
<Cdtr>
<PrTry>
<Id>2054</Id>
</PrTry>
<PFMSId>BORKH07259055</PFMSId>
<Tp/>
<Titl />
<Nm>BRUNDABAN SETHI</Nm>
<CdtrAcct>
<Id>
<Othr>
<BBAN>30607969086</BBAN>
<SOSE />
</Othr>
</Id>
</CdtrAcct>
</Cdtr>
<TxSts>ACCP</TxSts>
<StsRsnInf>
<Rsn>
<Cd/>
<AddtlInf/>
</Rsn>
</StsRsnInf>
<AddtlInfAPBS />
</CdtTrfTxInf>
<CdtTrfTxInf>
<PmtId>
<InstrId> S9540036</InstrId>
<EndToEndId>DlngHPowH0001SFIDS2017H182054</EndToEndId>
</PmtId>
<Amt>
<CtreAmt>0</CtreAmt>
<PrvcAmt>75000</PrvcAmt>
<InstdAmt>75000</InstdAmt>
</Amt>
<CdtrAgt>
<FinInstnId>
<BICFI>ODISHA GRAMYA BANK</BICFI>
<BrnchId>IOBA0ROGB01</BrnchId>
</FinInstnId>
</CdtrAgt>
<Cdtr>
<PrTry>
<Id>2054</Id>
</PrTry>
<PFMSId>BORKH04347124</PFMSId>
<Tp/>
<Titl />
<Nm>PRAMOD KU MANGARAJ</Nm>
<CdtrAcct>
<Id>
<Othr>
<BBAN>004001000007839</BBAN>
<SOSE />
</Othr>
</Id>
</CdtrAcct>
</Cdtr>
<TxSts>ACCP</TxSts>
<StsRsnInf>
<Rsn>
<Cd/>
<AddtlInf/>
</Rsn>
</StsRsnInf>
<AddtlInfAPBS />
</CdtTrfTxInf>
<CdtTrfTxInf>
<PmtId>
<InstrId> S9540036</InstrId>
<EndToEndId>DlngHPowH0002SFIDS2017H182054</EndToEndId>
</PmtId>
<Amt>
<CtreAmt>0</CtreAmt>
<PrvcAmt>75000</PrvcAmt>
<InstdAmt>75000</InstdAmt>
</Amt>
<CdtrAgt>
<FinInstnId>
<BICFI>BANK OF INDIA</BICFI>
<BrnchId>BKID0005119</BrnchId>
</FinInstnId>
</CdtrAgt>
<Cdtr>
<PrTry>
<Id>2054</Id>
</PrTry>
<PFMSId>BORKH07353227</PFMSId>
<Tp/>
<Titl />
<Nm>PRASANTA KUMAR PRADHAN</Nm>
<CdtrAcct>
<Id>
<Othr>
<BBAN>511910110001571</BBAN>
<SOSE />
</Othr>
</Id>
</CdtrAcct>
</Cdtr>
<TxSts>ACCP</TxSts>
<StsRsnInf>
<Rsn>
<Cd/>
<AddtlInf/>
</Rsn>
</StsRsnInf>
<AddtlInfAPBS />
</CdtTrfTxInf>
<CdtTrfTxInf>
<PmtId>
<InstrId> S9540036</InstrId>
<EndToEndId>DnklHPowH0007SFIDS2017H182054</EndToEndId>
</PmtId>
<Amt>
<CtreAmt>0</CtreAmt>
<PrvcAmt>75000</PrvcAmt>
<InstdAmt>75000</InstdAmt>
</Amt>
<CdtrAgt>
<FinInstnId>
<BICFI>UNITED BANK OF INDIA</BICFI>
<BrnchId>UTBI0DHLJ33</BrnchId>
</FinInstnId>
</CdtrAgt>
<Cdtr>
<PrTry>
<Id>2054</Id>
</PrTry>
<PFMSId>BORKH03349345</PFMSId>
<Tp/>
<Titl />
<Nm>AJAYA KUMAR SAHOO</Nm>
<CdtrAcct>
<Id>
<Othr>
<BBAN>0935010108192</BBAN>
<SOSE />
</Othr>
</Id>
</CdtrAcct>
</Cdtr>
<TxSts>ACCP</TxSts>
<StsRsnInf>
<Rsn>
<Cd/>
<AddtlInf/>
</Rsn>
</StsRsnInf>
<AddtlInfAPBS />
</CdtTrfTxInf>
<CdtTrfTxInf>
<PmtId>
<InstrId> S9540036</InstrId>
<EndToEndId>JatnHPowH0002SFIDS2017H182054</EndToEndId>
</PmtId>
<Amt>
<CtreAmt>0</CtreAmt>
<PrvcAmt>75000</PrvcAmt>
<InstdAmt>75000</InstdAmt>
</Amt>
<CdtrAgt>
<FinInstnId>
<BICFI>CANARA BANK</BICFI>
<BrnchId>CNRB0003673</BrnchId>
</FinInstnId>
</CdtrAgt>
<Cdtr>
<PrTry>
<Id>2054</Id>
</PrTry>
<PFMSId>BORKH08073999</PFMSId>
<Tp/>
<Titl />
<Nm>PRATAP KUMAR MOHANTY</Nm>
<CdtrAcct>
<Id>
<Othr>
<BBAN>3673101005996</BBAN>
<SOSE />
</Othr>
</Id>
</CdtrAcct>
</Cdtr>
<TxSts>ACCP</TxSts>
<StsRsnInf>
<Rsn>
<Cd/>
<AddtlInf/>
</Rsn>
</StsRsnInf>
<AddtlInfAPBS />
</CdtTrfTxInf>
<CdtTrfTxInf>
<PmtId>
<InstrId> S9540036</InstrId>
<EndToEndId>JlswHPowH0012SFIDS2017H182054</EndToEndId>
</PmtId>
<Amt>
<CtreAmt>0</CtreAmt>
<PrvcAmt>75000</PrvcAmt>
<InstdAmt>75000</InstdAmt>
</Amt>
<CdtrAgt>
<FinInstnId>
<BICFI>ORIENTAL BANK OF COMMERCE</BICFI>
<BrnchId>ORBC0101546</BrnchId>
</FinInstnId>
</CdtrAgt>
<Cdtr>
<PrTry>
<Id>2054</Id>
</PrTry>
<PFMSId>BORKH06149976</PFMSId>
<Tp/>
<Titl />
<Nm>NARAYAN CHAND</Nm>
<CdtrAcct>
<Id>
<Othr>
<BBAN>15462011000585</BBAN>
<SOSE />
</Othr>
</Id>
</CdtrAcct>
</Cdtr>
<TxSts>ACCP</TxSts>
<StsRsnInf>
<Rsn>
<Cd/>
<AddtlInf/>
</Rsn>
</StsRsnInf>
<AddtlInfAPBS />
</CdtTrfTxInf>
<CdtTrfTxInf>
<PmtId>
<InstrId> S9540036</InstrId>
<EndToEndId>JlswHRotH0008SFIDS2017H182054</EndToEndId>
</PmtId>
<Amt>
<CtreAmt>0</CtreAmt>
<PrvcAmt>80000</PrvcAmt>
<InstdAmt>80000</InstdAmt>
</Amt>
<CdtrAgt>
<FinInstnId>
<BICFI>ORIENTAL BANK OF COMMERCE</BICFI>
<BrnchId>ORBC0101546</BrnchId>
</FinInstnId>
</CdtrAgt>
<Cdtr>
<PrTry>
<Id>2054</Id>
</PrTry>
<PFMSId>BORKH04640260</PFMSId>
<Tp/>
<Titl />
<Nm>SUBAL PATRA</Nm>
<CdtrAcct>
<Id>
<Othr>
<BBAN>15462191009194</BBAN>
<SOSE />
</Othr>
</Id>
</CdtrAcct>
</Cdtr>
<TxSts>ACCP</TxSts>
<StsRsnInf>
<Rsn>
<Cd/>
<AddtlInf/>
</Rsn>
</StsRsnInf>
<AddtlInfAPBS />
</CdtTrfTxInf>
<CdtTrfTxInf>
<PmtId>
<InstrId> S9540036</InstrId>
<EndToEndId>KamgHPowH0003SFIDS2017H182054</EndToEndId>
</PmtId>
<Amt>
<CtreAmt>0</CtreAmt>
<PrvcAmt>75000</PrvcAmt>
<InstdAmt>75000</InstdAmt>
</Amt>
<CdtrAgt>
<FinInstnId>
<BICFI>STATE BANK OF INDIA</BICFI>
<BrnchId>SBIN0005759</BrnchId>
</FinInstnId>
</CdtrAgt>
<Cdtr>
<PrTry>
<Id>2054</Id>
</PrTry>
<PFMSId>BORKH08128803</PFMSId>
<Tp/>
<Titl />
<Nm>GOURANGA MAHARANA</Nm>
<CdtrAcct>
<Id>
<Othr>
<BBAN>34468495147</BBAN>
<SOSE />
</Othr>
</Id>
</CdtrAcct>
</Cdtr>
<TxSts>ACCP</TxSts>
<StsRsnInf>
<Rsn>
<Cd/>
<AddtlInf/>
</Rsn>
</StsRsnInf>
<AddtlInfAPBS />
</CdtTrfTxInf>
<CdtTrfTxInf>
<PmtId>
<InstrId> S9540036</InstrId>
<EndToEndId>KandHPowH0005SFIDS2017H182054</EndToEndId>
</PmtId>
<Amt>
<CtreAmt>0</CtreAmt>
<PrvcAmt>75000</PrvcAmt>
<InstdAmt>75000</InstdAmt>
</Amt>
<CdtrAgt>
<FinInstnId>
<BICFI>STATE BANK OF INDIA</BICFI>
<BrnchId>SBIN0009841</BrnchId>
</FinInstnId>
</CdtrAgt>
<Cdtr>
<PrTry>
<Id>2054</Id>
</PrTry>
<PFMSId>BORKH04236628</PFMSId>
<Tp/>
<Titl />
<Nm>NEHERU SAHOO</Nm>
<CdtrAcct>
<Id>
<Othr>
<BBAN>34762863730</BBAN>
<SOSE />
</Othr>
</Id>
</CdtrAcct>
</Cdtr>
<TxSts>ACCP</TxSts>
<StsRsnInf>
<Rsn>
<Cd/>
<AddtlInf/>
</Rsn>
</StsRsnInf>
<AddtlInfAPBS />
</CdtTrfTxInf>
<CdtTrfTxInf>
<PmtId>
<InstrId> S9540036</InstrId>
<EndToEndId>KandHPowH0009SFIDS2017H182054</EndToEndId>
</PmtId>
<Amt>
<CtreAmt>0</CtreAmt>
<PrvcAmt>75000</PrvcAmt>
<InstdAmt>75000</InstdAmt>
</Amt>
<CdtrAgt>
<FinInstnId>
<BICFI>STATE BANK OF INDIA</BICFI>
<BrnchId>SBIN0006545</BrnchId>
</FinInstnId>
</CdtrAgt>
<Cdtr>
<PrTry>
<Id>2054</Id>
</PrTry>
<PFMSId>BORKH07891501</PFMSId>
<Tp/>
<Titl />
<Nm>Golak Bihari Sahoo</Nm>
<CdtrAcct>
<Id>
<Othr>
<BBAN>30424364475</BBAN>
<SOSE />
</Othr>
</Id>
</CdtrAcct>
</Cdtr>
<TxSts>ACCP</TxSts>
<StsRsnInf>
<Rsn>
<Cd/>
<AddtlInf/>
</Rsn>
</StsRsnInf>
<AddtlInfAPBS />
</CdtTrfTxInf>
<CdtTrfTxInf>
<PmtId>
<InstrId> S9540036</InstrId>
<EndToEndId>KeonHPowH0012SFIDS2017H182054</EndToEndId>
</PmtId>
<Amt>
<CtreAmt>0</CtreAmt>
<PrvcAmt>75000</PrvcAmt>
<InstdAmt>75000</InstdAmt>
</Amt>
<CdtrAgt>
<FinInstnId>
<BICFI>BANK OF BARODA</BICFI>
<BrnchId>BARB0KEONJH</BrnchId>
</FinInstnId>
</CdtrAgt>
<Cdtr>
<PrTry>
<Id>2054</Id>
</PrTry>
<PFMSId>BORKH07966338</PFMSId>
<Tp/>
<Titl />
<Nm>NILAKANTHA DIKHIT</Nm>
<CdtrAcct>
<Id>
<Othr>
<BBAN>14990100003174</BBAN>
<SOSE />
</Othr>
</Id>
</CdtrAcct>
</Cdtr>
<TxSts>ACCP</TxSts>
<StsRsnInf>
<Rsn>
<Cd/>
<AddtlInf/>
</Rsn>
</StsRsnInf>
<AddtlInfAPBS />
</CdtTrfTxInf>
<CdtTrfTxInf>
<PmtId>
<InstrId> S9540036</InstrId>
<EndToEndId>KHRBHSplH0004SFIDS2017H182054</EndToEndId>
</PmtId>
<Amt>
<CtreAmt>0</CtreAmt>
<PrvcAmt>22250</PrvcAmt>
<InstdAmt>22250</InstdAmt>
</Amt>
<CdtrAgt>
<FinInstnId>
<BICFI>STATE BANK OF INDIA</BICFI>
<BrnchId>SBIN0006129</BrnchId>
</FinInstnId>
</CdtrAgt>
<Cdtr>
<PrTry>
<Id>2054</Id>
</PrTry>
<PFMSId>BORKH03635033</PFMSId>
<Tp/>
<Titl />
<Nm>GOPINATH ROUT</Nm>
<CdtrAcct>
<Id>
<Othr>
<BBAN>11702768600</BBAN>
<SOSE />
</Othr>
</Id>
</CdtrAcct>
</Cdtr>
<TxSts>ACCP</TxSts>
<StsRsnInf>
<Rsn>
<Cd/>
<AddtlInf/>
</Rsn>
</StsRsnInf>
<AddtlInfAPBS />
</CdtTrfTxInf>
<CdtTrfTxInf>
<PmtId>
<InstrId> S9540036</InstrId>
<EndToEndId>KKDHHRotH0004SFIDS2017H182054</EndToEndId>
</PmtId>
<Amt>
<CtreAmt>0</CtreAmt>
<PrvcAmt>80000</PrvcAmt>
<InstdAmt>80000</InstdAmt>
</Amt>
<CdtrAgt>
<FinInstnId>
<BICFI>STATE BANK OF INDIA</BICFI>
<BrnchId>SBIN0005753</BrnchId>
</FinInstnId>
</CdtrAgt>
<Cdtr>
<PrTry>
<Id>2054</Id>
</PrTry>
<PFMSId>BORKH05242332</PFMSId>
<Tp/>
<Titl />
<Nm>RABINDRA NATH BHUYAN</Nm>
<CdtrAcct>
<Id>
<Othr>
<BBAN>31700240888</BBAN>
<SOSE />
</Othr>
</Id>
</CdtrAcct>
</Cdtr>
<TxSts>ACCP</TxSts>
<StsRsnInf>
<Rsn>
<Cd/>
<AddtlInf/>
</Rsn>
</StsRsnInf>
<AddtlInfAPBS />
</CdtTrfTxInf>
<CdtTrfTxInf>
<PmtId>
<InstrId> S9540036</InstrId>
<EndToEndId>KLKTHSplH0003SFIDS2017H182054</EndToEndId>
</PmtId>
<Amt>
<CtreAmt>0</CtreAmt>
<PrvcAmt>70000</PrvcAmt>
<InstdAmt>70000</InstdAmt>
</Amt>
<CdtrAgt>
<FinInstnId>
<BICFI>STATE BANK OF INDIA</BICFI>
<BrnchId>SBIN0012103</BrnchId>
</FinInstnId>
</CdtrAgt>
<Cdtr>
<PrTry>
<Id>2054</Id>
</PrTry>
<PFMSId>BORKH07259049</PFMSId>
<Tp/>
<Titl />
<Nm>PANCHU  SWAIN</Nm>
<CdtrAcct>
<Id>
<Othr>
<BBAN>32304893649</BBAN>
<SOSE />
</Othr>
</Id>
</CdtrAcct>
</Cdtr>
<TxSts>ACCP</TxSts>
<StsRsnInf>
<Rsn>
<Cd/>
<AddtlInf/>
</Rsn>
</StsRsnInf>
<AddtlInfAPBS />
</CdtTrfTxInf>
<CdtTrfTxInf>
<PmtId>
<InstrId> S9540036</InstrId>
<EndToEndId>KndrHRotH0001SFIDS2017H182054</EndToEndId>
</PmtId>
<Amt>
<CtreAmt>0</CtreAmt>
<PrvcAmt>80000</PrvcAmt>
<InstdAmt>80000</InstdAmt>
</Amt>
<CdtrAgt>
<FinInstnId>
<BICFI>CENTRAL BANK OF INDIA</BICFI>
<BrnchId>CBIN0284191</BrnchId>
</FinInstnId>
</CdtrAgt>
<Cdtr>
<PrTry>
<Id>2054</Id>
</PrTry>
<PFMSId>BORKH07861732</PFMSId>
<Tp/>
<Titl />
<Nm>PRADIPTA KUMAR SAHU</Nm>
<CdtrAcct>
<Id>
<Othr>
<BBAN>3321660495</BBAN>
<SOSE />
</Othr>
</Id>
</CdtrAcct>
</Cdtr>
<TxSts>ACCP</TxSts>
<StsRsnInf>
<Rsn>
<Cd/>
<AddtlInf/>
</Rsn>
</StsRsnInf>
<AddtlInfAPBS />
</CdtTrfTxInf>
<CdtTrfTxInf>
<PmtId>
<InstrId> S9540036</InstrId>
<EndToEndId>KpsdHPowH0001SFIDS2016H172054</EndToEndId>
</PmtId>
<Amt>
<CtreAmt>0</CtreAmt>
<PrvcAmt>75000</PrvcAmt>
<InstdAmt>75000</InstdAmt>
</Amt>
<CdtrAgt>
<FinInstnId>
<BICFI>STATE BANK OF INDIA</BICFI>
<BrnchId>SBIN0008215</BrnchId>
</FinInstnId>
</CdtrAgt>
<Cdtr>
<PrTry>
<Id>2054</Id>
</PrTry>
<PFMSId>BORKH03777363</PFMSId>
<Tp/>
<Titl />
<Nm>ABANI KUMAR BISWAL</Nm>
<CdtrAcct>
<Id>
<Othr>
<BBAN>30650044614</BBAN>
<SOSE />
</Othr>
</Id>
</CdtrAcct>
</Cdtr>
<TxSts>ACCP</TxSts>
<StsRsnInf>
<Rsn>
<Cd/>
<AddtlInf/>
</Rsn>
</StsRsnInf>
<AddtlInfAPBS />
</CdtTrfTxInf>
<CdtTrfTxInf>
<PmtId>
<InstrId> S9540036</InstrId>
<EndToEndId>KrdaHPowH0003SFIDS2017H182054</EndToEndId>
</PmtId>
<Amt>
<CtreAmt>0</CtreAmt>
<PrvcAmt>75000</PrvcAmt>
<InstdAmt>75000</InstdAmt>
</Amt>
<CdtrAgt>
<FinInstnId>
<BICFI>PUNJAB NATIONAL BANK</BICFI>
<BrnchId>PUNB0737300</BrnchId>
</FinInstnId>
</CdtrAgt>
<Cdtr>
<PrTry>
<Id>2054</Id>
</PrTry>
<PFMSId>BORKH08612000</PFMSId>
<Tp/>
<Titl />
<Nm>DILLIP KUMAR JENA</Nm>
<CdtrAcct>
<Id>
<Othr>
<BBAN>7373000100015562</BBAN>
<SOSE />
</Othr>
</Id>
</CdtrAcct>
</Cdtr>
<TxSts>ACCP</TxSts>
<StsRsnInf>
<Rsn>
<Cd/>
<AddtlInf/>
</Rsn>
</StsRsnInf>
<AddtlInfAPBS />
</CdtTrfTxInf>
<CdtTrfTxInf>
<PmtId>
<InstrId> S9540036</InstrId>
<EndToEndId>KsumHRotH0002SFIDS2017H182054</EndToEndId>
</PmtId>
<Amt>
<CtreAmt>0</CtreAmt>
<PrvcAmt>80000</PrvcAmt>
<InstdAmt>80000</InstdAmt>
</Amt>
<CdtrAgt>
<FinInstnId>
<BICFI>STATE BANK OF INDIA</BICFI>
<BrnchId>SBIN0000163</BrnchId>
</FinInstnId>
</CdtrAgt>
<Cdtr>
<PrTry>
<Id>2054</Id>
</PrTry>
<PFMSId>BORKH08391273</PFMSId>
<Tp/>
<Titl />
<Nm>PARTHASARATHI GIRI</Nm>
<CdtrAcct>
<Id>
<Othr>
<BBAN>30893476240</BBAN>
<SOSE />
</Othr>
</Id>
</CdtrAcct>
</Cdtr>
<TxSts>ACCP</TxSts>
<StsRsnInf>
<Rsn>
<Cd/>
<AddtlInf/>
</Rsn>
</StsRsnInf>
<AddtlInfAPBS />
</CdtTrfTxInf>
<CdtTrfTxInf>
<PmtId>
<InstrId> S9540036</InstrId>
<EndToEndId>KujnHRotH0003SFIDS2017H182054</EndToEndId>
</PmtId>
<Amt>
<CtreAmt>0</CtreAmt>
<PrvcAmt>80000</PrvcAmt>
<InstdAmt>80000</InstdAmt>
</Amt>
<CdtrAgt>
<FinInstnId>
<BICFI>ALLAHABAD BANK</BICFI>
<BrnchId>ALLA0211689</BrnchId>
</FinInstnId>
</CdtrAgt>
<Cdtr>
<PrTry>
<Id>2054</Id>
</PrTry>
<PFMSId>BORKH04338365</PFMSId>
<Tp/>
<Titl />
<Nm>JAGABANDHU ROUT</Nm>
<CdtrAcct>
<Id>
<Othr>
<BBAN>22300951269</BBAN>
<SOSE />
</Othr>
</Id>
</CdtrAcct>
</Cdtr>
<TxSts>ACCP</TxSts>
<StsRsnInf>
<Rsn>
<Cd/>
<AddtlInf/>
</Rsn>
</StsRsnInf>
<AddtlInfAPBS />
</CdtTrfTxInf>
<CdtTrfTxInf>
<PmtId>
<InstrId> S9540036</InstrId>
<EndToEndId>KujnHRotH0010SFIDS2017H182054</EndToEndId>
</PmtId>
<Amt>
<CtreAmt>0</CtreAmt>
<PrvcAmt>79500</PrvcAmt>
<InstdAmt>79500</InstdAmt>
</Amt>
<CdtrAgt>
<FinInstnId>
<BICFI>STATE BANK OF INDIA</BICFI>
<BrnchId>SBIN0010916</BrnchId>
</FinInstnId>
</CdtrAgt>
<Cdtr>
<PrTry>
<Id>2054</Id>
</PrTry>
<PFMSId>BORKH06623140</PFMSId>
<Tp/>
<Titl />
<Nm>Kailash Swain </Nm>
<CdtrAcct>
<Id>
<Othr>
<BBAN>34510047356</BBAN>
<SOSE />
</Othr>
</Id>
</CdtrAcct>
</Cdtr>
<TxSts>ACCP</TxSts>
<StsRsnInf>
<Rsn>
<Cd/>
<AddtlInf/>
</Rsn>
</StsRsnInf>
<AddtlInfAPBS />
</CdtTrfTxInf>
<CdtTrfTxInf>
<PmtId>
<InstrId> S9540036</InstrId>
<EndToEndId>KuliHPowH0006SFIDS2017H182054</EndToEndId>
</PmtId>
<Amt>
<CtreAmt>0</CtreAmt>
<PrvcAmt>75000</PrvcAmt>
<InstdAmt>75000</InstdAmt>
</Amt>
<CdtrAgt>
<FinInstnId>
<BICFI>ODISHA GRAMYA BANK</BICFI>
<BrnchId>IOBA0ROGB01</BrnchId>
</FinInstnId>
</CdtrAgt>
<Cdtr>
<PrTry>
<Id>2054</Id>
</PrTry>
<PFMSId>BORKH04200828</PFMSId>
<Tp/>
<Titl />
<Nm>GOPINATH MARANDI</Nm>
<CdtrAcct>
<Id>
<Othr>
<BBAN>102610400008237</BBAN>
<SOSE />
</Othr>
</Id>
</CdtrAcct>
</Cdtr>
<TxSts>ACCP</TxSts>
<StsRsnInf>
<Rsn>
<Cd/>
<AddtlInf/>
</Rsn>
</StsRsnInf>
<AddtlInfAPBS />
</CdtTrfTxInf>
<CdtTrfTxInf>
<PmtId>
<InstrId> S9540036</InstrId>
<EndToEndId>KuliHPowH0008SFIDS2017H182054</EndToEndId>
</PmtId>
<Amt>
<CtreAmt>0</CtreAmt>
<PrvcAmt>75000</PrvcAmt>
<InstdAmt>75000</InstdAmt>
</Amt>
<CdtrAgt>
<FinInstnId>
<BICFI>STATE BANK OF INDIA</BICFI>
<BrnchId>SBIN0006470</BrnchId>
</FinInstnId>
</CdtrAgt>
<Cdtr>
<PrTry>
<Id>2054</Id>
</PrTry>
<PFMSId>BORKH04506997</PFMSId>
<Tp/>
<Titl />
<Nm>DILLIP KUMAR MANGAL</Nm>
<CdtrAcct>
<Id>
<Othr>
<BBAN>20083291130</BBAN>
<SOSE />
</Othr>
</Id>
</CdtrAcct>
</Cdtr>
<TxSts>ACCP</TxSts>
<StsRsnInf>
<Rsn>
<Cd/>
<AddtlInf/>
</Rsn>
</StsRsnInf>
<AddtlInfAPBS />
</CdtTrfTxInf>
<CdtTrfTxInf>
<PmtId>
<InstrId> S9540036</InstrId>
<EndToEndId>MHNGHRotH0008SFIDS2017H182054</EndToEndId>
</PmtId>
<Amt>
<CtreAmt>0</CtreAmt>
<PrvcAmt>80000</PrvcAmt>
<InstdAmt>80000</InstdAmt>
</Amt>
<CdtrAgt>
<FinInstnId>
<BICFI>STATE BANK OF INDIA</BICFI>
<BrnchId>SBIN0003942</BrnchId>
</FinInstnId>
</CdtrAgt>
<Cdtr>
<PrTry>
<Id>2054</Id>
</PrTry>
<PFMSId>BORKH08580481</PFMSId>
<Tp/>
<Titl />
<Nm>RENUBALA KAR</Nm>
<CdtrAcct>
<Id>
<Othr>
<BBAN>31514553485</BBAN>
<SOSE />
</Othr>
</Id>
</CdtrAcct>
</Cdtr>
<TxSts>ACCP</TxSts>
<StsRsnInf>
<Rsn>
<Cd/>
<AddtlInf/>
</Rsn>
</StsRsnInf>
<AddtlInfAPBS />
</CdtTrfTxInf>
<CdtTrfTxInf>
<PmtId>
<InstrId> S9540036</InstrId>
<EndToEndId>MordHPowH0002SFIDS2017H182054</EndToEndId>
</PmtId>
<Amt>
<CtreAmt>0</CtreAmt>
<PrvcAmt>75000</PrvcAmt>
<InstdAmt>75000</InstdAmt>
</Amt>
<CdtrAgt>
<FinInstnId>
<BICFI>UNITED BANK OF INDIA</BICFI>
<BrnchId>UTBI0RGV451</BrnchId>
</FinInstnId>
</CdtrAgt>
<Cdtr>
<PrTry>
<Id>2054</Id>
</PrTry>
<PFMSId>BORKH08054183</PFMSId>
<Tp/>
<Titl />
<Nm>MENAKARANI SETHI</Nm>
<CdtrAcct>
<Id>
<Othr>
<BBAN>0547010116374</BBAN>
<SOSE />
</Othr>
</Id>
</CdtrAcct>
</Cdtr>
<TxSts>ACCP</TxSts>
<StsRsnInf>
<Rsn>
<Cd/>
<AddtlInf/>
</Rsn>
</StsRsnInf>
<AddtlInfAPBS />
</CdtTrfTxInf>
<CdtTrfTxInf>
<PmtId>
<InstrId> S9540036</InstrId>
<EndToEndId>MordHPowH0007SFIDS2017H182054</EndToEndId>
</PmtId>
<Amt>
<CtreAmt>0</CtreAmt>
<PrvcAmt>75000</PrvcAmt>
<InstdAmt>75000</InstdAmt>
</Amt>
<CdtrAgt>
<FinInstnId>
<BICFI>UNITED BANK OF INDIA</BICFI>
<BrnchId>UTBI0GADJ25</BrnchId>
</FinInstnId>
</CdtrAgt>
<Cdtr>
<PrTry>
<Id>2054</Id>
</PrTry>
<PFMSId>BORKH04201794</PFMSId>
<Tp/>
<Titl />
<Nm>NIRANJAN SETHI</Nm>
<CdtrAcct>
<Id>
<Othr>
<BBAN>0903010200786</BBAN>
<SOSE />
</Othr>
</Id>
</CdtrAcct>
</Cdtr>
<TxSts>ACCP</TxSts>
<StsRsnInf>
<Rsn>
<Cd/>
<AddtlInf/>
</Rsn>
</StsRsnInf>
<AddtlInfAPBS />
</CdtTrfTxInf>
<CdtTrfTxInf>
<PmtId>
<InstrId> S9540036</InstrId>
<EndToEndId>MordHPowH0008SFIDS2017H182054</EndToEndId>
</PmtId>
<Amt>
<CtreAmt>0</CtreAmt>
<PrvcAmt>75000</PrvcAmt>
<InstdAmt>75000</InstdAmt>
</Amt>
<CdtrAgt>
<FinInstnId>
<BICFI>STATE BANK OF INDIA</BICFI>
<BrnchId>SBIN0010932</BrnchId>
</FinInstnId>
</CdtrAgt>
<Cdtr>
<PrTry>
<Id>2054</Id>
</PrTry>
<PFMSId>BORKH07374874</PFMSId>
<Tp/>
<Titl />
<Nm>BIBHUTI BHUSAN MOHANTA</Nm>
<CdtrAcct>
<Id>
<Othr>
<BBAN>31469541152</BBAN>
<SOSE />
</Othr>
</Id>
</CdtrAcct>
</Cdtr>
<TxSts>ACCP</TxSts>
<StsRsnInf>
<Rsn>
<Cd/>
<AddtlInf/>
</Rsn>
</StsRsnInf>
<AddtlInfAPBS />
</CdtTrfTxInf>
<CdtTrfTxInf>
<PmtId>
<InstrId> S9540036</InstrId>
<EndToEndId>MrshHPowH0009SFIDS2017H182054</EndToEndId>
</PmtId>
<Amt>
<CtreAmt>0</CtreAmt>
<PrvcAmt>75000</PrvcAmt>
<InstdAmt>75000</InstdAmt>
</Amt>
<CdtrAgt>
<FinInstnId>
<BICFI>ODISHA GRAMYA BANK</BICFI>
<BrnchId>IOBA0ROGB01</BrnchId>
</FinInstnId>
</CdtrAgt>
<Cdtr>
<PrTry>
<Id>2054</Id>
</PrTry>
<PFMSId>BORKH04971609</PFMSId>
<Tp/>
<Titl />
<Nm>MANORANJAN DAS</Nm>
<CdtrAcct>
<Id>
<Othr>
<BBAN>40640100002328</BBAN>
<SOSE />
</Othr>
</Id>
</CdtrAcct>
</Cdtr>
<TxSts>ACCP</TxSts>
<StsRsnInf>
<Rsn>
<Cd/>
<AddtlInf/>
</Rsn>
</StsRsnInf>
<AddtlInfAPBS />
</CdtTrfTxInf>
<CdtTrfTxInf>
<PmtId>
<InstrId> S9540036</InstrId>
<EndToEndId>OdopHPowH0003SFIDS2016H172054</EndToEndId>
</PmtId>
<Amt>
<CtreAmt>0</CtreAmt>
<PrvcAmt>75000</PrvcAmt>
<InstdAmt>75000</InstdAmt>
</Amt>
<CdtrAgt>
<FinInstnId>
<BICFI>ANDHRA BANK</BICFI>
<BrnchId>ANDB0001288</BrnchId>
</FinInstnId>
</CdtrAgt>
<Cdtr>
<PrTry>
<Id>2054</Id>
</PrTry>
<PFMSId>BORKH04375814</PFMSId>
<Tp/>
<Titl />
<Nm>BHOLESHWAR SAHOO</Nm>
<CdtrAcct>
<Id>
<Othr>
<BBAN>128810100010828</BBAN>
<SOSE />
</Othr>
</Id>
</CdtrAcct>
</Cdtr>
<TxSts>ACCP</TxSts>
<StsRsnInf>
<Rsn>
<Cd/>
<AddtlInf/>
</Rsn>
</StsRsnInf>
<AddtlInfAPBS />
</CdtTrfTxInf>
<CdtTrfTxInf>
<PmtId>
<InstrId> S9540036</InstrId>
<EndToEndId>PattHSplH0002SFIDS2017H182054</EndToEndId>
</PmtId>
<Amt>
<CtreAmt>0</CtreAmt>
<PrvcAmt>70000</PrvcAmt>
<InstdAmt>70000</InstdAmt>
</Amt>
<CdtrAgt>
<FinInstnId>
<BICFI>INDIAN BANK</BICFI>
<BrnchId>IDIB000O018</BrnchId>
</FinInstnId>
</CdtrAgt>
<Cdtr>
<PrTry>
<Id>2054</Id>
</PrTry>
<PFMSId>BORKH04182977</PFMSId>
<Tp/>
<Titl />
<Nm>BABAJI CHARAN SAHOO</Nm>
<CdtrAcct>
<Id>
<Othr>
<BBAN>591111489</BBAN>
<SOSE />
</Othr>
</Id>
</CdtrAcct>
</Cdtr>
<TxSts>ACCP</TxSts>
<StsRsnInf>
<Rsn>
<Cd/>
<AddtlInf/>
</Rsn>
</StsRsnInf>
<AddtlInfAPBS />
</CdtTrfTxInf>
<CdtTrfTxInf>
<PmtId>
<InstrId> S9540036</InstrId>
<EndToEndId>PpliHComH0001SFIDS2016H172054</EndToEndId>
</PmtId>
<Amt>
<CtreAmt>0</CtreAmt>
<PrvcAmt>600000</PrvcAmt>
<InstdAmt>600000</InstdAmt>
</Amt>
<CdtrAgt>
<FinInstnId>
<BICFI>STATE BANK OF INDIA (SBH)</BICFI>
<BrnchId>SBHY0021893</BrnchId>
</FinInstnId>
</CdtrAgt>
<Cdtr>
<PrTry>
<Id>2054</Id>
</PrTry>
<PFMSId>BORKH06057863</PFMSId>
<Tp/>
<Titl />
<Nm>DHANESWAR BARAL</Nm>
<CdtrAcct>
<Id>
<Othr>
<BBAN>52209526485</BBAN>
<SOSE />
</Othr>
</Id>
</CdtrAcct>
</Cdtr>
<TxSts>ACCP</TxSts>
<StsRsnInf>
<Rsn>
<Cd/>
<AddtlInf/>
</Rsn>
</StsRsnInf>
<AddtlInfAPBS />
</CdtTrfTxInf>
<CdtTrfTxInf>
<PmtId>
<InstrId> S9540036</InstrId>
<EndToEndId>PpliHComH0001SFIDS2017H182054</EndToEndId>
</PmtId>
<Amt>
<CtreAmt>0</CtreAmt>
<PrvcAmt>600000</PrvcAmt>
<InstdAmt>600000</InstdAmt>
</Amt>
<CdtrAgt>
<FinInstnId>
<BICFI>HDFC BANK LTD</BICFI>
<BrnchId>HDFC0002396</BrnchId>
</FinInstnId>
</CdtrAgt>
<Cdtr>
<PrTry>
<Id>2054</Id>
</PrTry>
<PFMSId>BORKH08356565</PFMSId>
<Tp/>
<Titl />
<Nm>SURYAKANTA PANDA</Nm>
<CdtrAcct>
<Id>
<Othr>
<BBAN>50100142459240</BBAN>
<SOSE />
</Othr>
</Id>
</CdtrAcct>
</Cdtr>
<TxSts>ACCP</TxSts>
<StsRsnInf>
<Rsn>
<Cd/>
<AddtlInf/>
</Rsn>
</StsRsnInf>
<AddtlInfAPBS />
</CdtTrfTxInf>
<CdtTrfTxInf>
<PmtId>
<InstrId> S9540036</InstrId>
<EndToEndId>PpliHRotH0004SFIDS2017H182054</EndToEndId>
</PmtId>
<Amt>
<CtreAmt>0</CtreAmt>
<PrvcAmt>80000</PrvcAmt>
<InstdAmt>80000</InstdAmt>
</Amt>
<CdtrAgt>
<FinInstnId>
<BICFI>INDIAN OVERSEAS BANK</BICFI>
<BrnchId>IOBA0003050</BrnchId>
</FinInstnId>
</CdtrAgt>
<Cdtr>
<PrTry>
<Id>2054</Id>
</PrTry>
<PFMSId>BORKH07376224</PFMSId>
<Tp/>
<Titl />
<Nm>TULU PRADHAN</Nm>
<CdtrAcct>
<Id>
<Othr>
<BBAN>305001000000563</BBAN>
<SOSE />
</Othr>
</Id>
</CdtrAcct>
</Cdtr>
<TxSts>ACCP</TxSts>
<StsRsnInf>
<Rsn>
<Cd/>
<AddtlInf/>
</Rsn>
</StsRsnInf>
<AddtlInfAPBS />
</CdtTrfTxInf>
<CdtTrfTxInf>
<PmtId>
<InstrId> S9540036</InstrId>
<EndToEndId>PurrHSplH0005SFIDS2017H182054</EndToEndId>
</PmtId>
<Amt>
<CtreAmt>0</CtreAmt>
<PrvcAmt>70000</PrvcAmt>
<InstdAmt>70000</InstdAmt>
</Amt>
<CdtrAgt>
<FinInstnId>
<BICFI>STATE BANK OF INDIA</BICFI>
<BrnchId>SBIN0002073</BrnchId>
</FinInstnId>
</CdtrAgt>
<Cdtr>
<PrTry>
<Id>2054</Id>
</PrTry>
<PFMSId>BORKH06892491</PFMSId>
<Tp/>
<Titl />
<Nm>Hina Bisoyi</Nm>
<CdtrAcct>
<Id>
<Othr>
<BBAN>31548561203</BBAN>
<SOSE />
</Othr>
</Id>
</CdtrAcct>
</Cdtr>
<TxSts>ACCP</TxSts>
<StsRsnInf>
<Rsn>
<Cd/>
<AddtlInf/>
</Rsn>
</StsRsnInf>
<AddtlInfAPBS />
</CdtTrfTxInf>
<CdtTrfTxInf>
<PmtId>
<InstrId> S9540036</InstrId>
<EndToEndId>RajnHPowH0004SFIDS2016H172054</EndToEndId>
</PmtId>
<Amt>
<CtreAmt>0</CtreAmt>
<PrvcAmt>75000</PrvcAmt>
<InstdAmt>75000</InstdAmt>
</Amt>
<CdtrAgt>
<FinInstnId>
<BICFI>STATE BANK OF INDIA</BICFI>
<BrnchId>SBIN0012059</BrnchId>
</FinInstnId>
</CdtrAgt>
<Cdtr>
<PrTry>
<Id>2054</Id>
</PrTry>
<PFMSId>BORKH04241322</PFMSId>
<Tp/>
<Titl />
<Nm>NITYANANDA PALLAI</Nm>
<CdtrAcct>
<Id>
<Othr>
<BBAN>30921746119</BBAN>
<SOSE />
</Othr>
</Id>
</CdtrAcct>
</Cdtr>
<TxSts>ACCP</TxSts>
<StsRsnInf>
<Rsn>
<Cd/>
<AddtlInf/>
</Rsn>
</StsRsnInf>
<AddtlInfAPBS />
</CdtTrfTxInf>
<CdtTrfTxInf>
<PmtId>
<InstrId> S9540036</InstrId>
<EndToEndId>RmnaHPumH0004SFIDS2017H182054</EndToEndId>
</PmtId>
<Amt>
<CtreAmt>0</CtreAmt>
<PrvcAmt>15000</PrvcAmt>
<InstdAmt>15000</InstdAmt>
</Amt>
<CdtrAgt>
<FinInstnId>
<BICFI>STATE BANK OF INDIA</BICFI>
<BrnchId>SBIN0012053</BrnchId>
</FinInstnId>
</CdtrAgt>
<Cdtr>
<PrTry>
<Id>2054</Id>
</PrTry>
<PFMSId>BORKH06892418</PFMSId>
<Tp/>
<Titl />
<Nm>SUBAS CHANDRA HAJARA</Nm>
<CdtrAcct>
<Id>
<Othr>
<BBAN>36004671729</BBAN>
<SOSE />
</Othr>
</Id>
</CdtrAcct>
</Cdtr>
<TxSts>ACCP</TxSts>
<StsRsnInf>
<Rsn>
<Cd/>
<AddtlInf/>
</Rsn>
</StsRsnInf>
<AddtlInfAPBS />
</CdtTrfTxInf>
<CdtTrfTxInf>
<PmtId>
<InstrId> S9540036</InstrId>
<EndToEndId>RnprHRotH0002SFIDS2017H182054</EndToEndId>
</PmtId>
<Amt>
<CtreAmt>0</CtreAmt>
<PrvcAmt>80000</PrvcAmt>
<InstdAmt>80000</InstdAmt>
</Amt>
<CdtrAgt>
<FinInstnId>
<BICFI>STATE BANK OF INDIA</BICFI>
<BrnchId>SBIN0003943</BrnchId>
</FinInstnId>
</CdtrAgt>
<Cdtr>
<PrTry>
<Id>2054</Id>
</PrTry>
<PFMSId>BORKH05413928</PFMSId>
<Tp/>
<Titl />
<Nm>SUBAS CH SAHOO</Nm>
<CdtrAcct>
<Id>
<Othr>
<BBAN>11297483622</BBAN>
<SOSE />
</Othr>
</Id>
</CdtrAcct>
</Cdtr>
<TxSts>ACCP</TxSts>
<StsRsnInf>
<Rsn>
<Cd/>
<AddtlInf/>
</Rsn>
</StsRsnInf>
<AddtlInfAPBS />
</CdtTrfTxInf>
<CdtTrfTxInf>
<PmtId>
<InstrId> S9540036</InstrId>
<EndToEndId>RsnpHRotH0001SFIDS2017H182054</EndToEndId>
</PmtId>
<Amt>
<CtreAmt>0</CtreAmt>
<PrvcAmt>80000</PrvcAmt>
<InstdAmt>80000</InstdAmt>
</Amt>
<CdtrAgt>
<FinInstnId>
<BICFI>BANK OF INDIA</BICFI>
<BrnchId>BKID0005482</BrnchId>
</FinInstnId>
</CdtrAgt>
<Cdtr>
<PrTry>
<Id>2054</Id>
</PrTry>
<PFMSId>BORKH07775683</PFMSId>
<Tp/>
<Titl />
<Nm>LAXMIPRIYA BEHERA</Nm>
<CdtrAcct>
<Id>
<Othr>
<BBAN>548210510001047</BBAN>
<SOSE />
</Othr>
</Id>
</CdtrAcct>
</Cdtr>
<TxSts>ACCP</TxSts>
<StsRsnInf>
<Rsn>
<Cd/>
<AddtlInf/>
</Rsn>
</StsRsnInf>
<AddtlInfAPBS />
</CdtTrfTxInf>
<CdtTrfTxInf>
<PmtId>
<InstrId> S9540036</InstrId>
<EndToEndId>SarsHPowH0005SFIDS2017H182054</EndToEndId>
</PmtId>
<Amt>
<CtreAmt>0</CtreAmt>
<PrvcAmt>75000</PrvcAmt>
<InstdAmt>75000</InstdAmt>
</Amt>
<CdtrAgt>
<FinInstnId>
<BICFI>STATE BANK OF INDIA</BICFI>
<BrnchId>SBIN0006127</BrnchId>
</FinInstnId>
</CdtrAgt>
<Cdtr>
<PrTry>
<Id>2054</Id>
</PrTry>
<PFMSId>BORKH03490986</PFMSId>
<Tp/>
<Titl />
<Nm>SUSHIL CHANDRA MOHANTA</Nm>
<CdtrAcct>
<Id>
<Othr>
<BBAN>35110692746</BBAN>
<SOSE />
</Othr>
</Id>
</CdtrAcct>
</Cdtr>
<TxSts>ACCP</TxSts>
<StsRsnInf>
<Rsn>
<Cd/>
<AddtlInf/>
</Rsn>
</StsRsnInf>
<AddtlInfAPBS />
</CdtTrfTxInf>
<CdtTrfTxInf>
<PmtId>
<InstrId> S9540036</InstrId>
<EndToEndId>SRGHHRotH0003SFIDS2017H182054</EndToEndId>
</PmtId>
<Amt>
<CtreAmt>0</CtreAmt>
<PrvcAmt>80000</PrvcAmt>
<InstdAmt>80000</InstdAmt>
</Amt>
<CdtrAgt>
<FinInstnId>
<BICFI>UTKAL GRAMYA BANK</BICFI>
<BrnchId>SBIN0RRUKGB</BrnchId>
</FinInstnId>
</CdtrAgt>
<Cdtr>
<PrTry>
<Id>2054</Id>
</PrTry>
<PFMSId>BORKH03265940</PFMSId>
<Tp/>
<Titl />
<Nm>ARUNA KUMAR GOUDA</Nm>
<CdtrAcct>
<Id>
<Othr>
<BBAN>13520877597</BBAN>
<SOSE />
</Othr>
</Id>
</CdtrAcct>
</Cdtr>
<TxSts>ACCP</TxSts>
<StsRsnInf>
<Rsn>
<Cd/>
<AddtlInf/>
</Rsn>
</StsRsnInf>
<AddtlInfAPBS />
</CdtTrfTxInf>
<CdtTrfTxInf>
<PmtId>
<InstrId> S9540036</InstrId>
<EndToEndId>SulpHPowH0002SFIDS2016H172054</EndToEndId>
</PmtId>
<Amt>
<CtreAmt>0</CtreAmt>
<PrvcAmt>75000</PrvcAmt>
<InstdAmt>75000</InstdAmt>
</Amt>
<CdtrAgt>
<FinInstnId>
<BICFI>UNITED BANK OF INDIA</BICFI>
<BrnchId>UTBI0DEUJ24</BrnchId>
</FinInstnId>
</CdtrAgt>
<Cdtr>
<PrTry>
<Id>2054</Id>
</PrTry>
<PFMSId>BORKH04376675</PFMSId>
<Tp/>
<Titl />
<Nm>BHABATOSH KUMAR DAS</Nm>
<CdtrAcct>
<Id>
<Othr>
<BBAN>0902010105343</BBAN>
<SOSE />
</Othr>
</Id>
</CdtrAcct>
</Cdtr>
<TxSts>ACCP</TxSts>
<StsRsnInf>
<Rsn>
<Cd/>
<AddtlInf/>
</Rsn>
</StsRsnInf>
<AddtlInfAPBS />
</CdtTrfTxInf>
<CdtTrfTxInf>
<PmtId>
<InstrId> S9540036</InstrId>
<EndToEndId>TiroHRotH0005SFIDS2017H182054</EndToEndId>
</PmtId>
<Amt>
<CtreAmt>0</CtreAmt>
<PrvcAmt>80000</PrvcAmt>
<InstdAmt>80000</InstdAmt>
</Amt>
<CdtrAgt>
<FinInstnId>
<BICFI>STATE BANK OF INDIA</BICFI>
<BrnchId>SBIN0012045</BrnchId>
</FinInstnId>
</CdtrAgt>
<Cdtr>
<PrTry>
<Id>2054</Id>
</PrTry>
<PFMSId>BORKH03146702</PFMSId>
<Tp/>
<Titl />
<Nm>SOUMYA KANTA SWAIN</Nm>
<CdtrAcct>
<Id>
<Othr>
<BBAN>34399584012</BBAN>
<SOSE />
</Othr>
</Id>
</CdtrAcct>
</Cdtr>
<TxSts>ACCP</TxSts>
<StsRsnInf>
<Rsn>
<Cd/>
<AddtlInf/>
</Rsn>
</StsRsnInf>
<AddtlInfAPBS />
</CdtTrfTxInf>
<CdtTrfTxInf>
<PmtId>
<InstrId> S9540036</InstrId>
<EndToEndId>TiroHRotH0006SFIDS2017H182054</EndToEndId>
</PmtId>
<Amt>
<CtreAmt>0</CtreAmt>
<PrvcAmt>80000</PrvcAmt>
<InstdAmt>80000</InstdAmt>
</Amt>
<CdtrAgt>
<FinInstnId>
<BICFI>ODISHA GRAMYA BANK</BICFI>
<BrnchId>IOBA0ROGB01</BrnchId>
</FinInstnId>
</CdtrAgt>
<Cdtr>
<PrTry>
<Id>2054</Id>
</PrTry>
<PFMSId>BORKH03016399</PFMSId>
<Tp/>
<Titl />
<Nm>JADUNATH MANAHARI</Nm>
<CdtrAcct>
<Id>
<Othr>
<BBAN>40170100003429</BBAN>
<SOSE />
</Othr>
</Id>
</CdtrAcct>
</Cdtr>
<TxSts>ACCP</TxSts>
<StsRsnInf>
<Rsn>
<Cd/>
<AddtlInf/>
</Rsn>
</StsRsnInf>
<AddtlInfAPBS />
</CdtTrfTxInf>
<CdtTrfTxInf>
<PmtId>
<InstrId> S9540036</InstrId>
<EndToEndId>TiroHRotH0007SFIDS2017H182054</EndToEndId>
</PmtId>
<Amt>
<CtreAmt>0</CtreAmt>
<PrvcAmt>80000</PrvcAmt>
<InstdAmt>80000</InstdAmt>
</Amt>
<CdtrAgt>
<FinInstnId>
<BICFI>CENTRAL BANK OF INDIA</BICFI>
<BrnchId>CBIN0284086</BrnchId>
</FinInstnId>
</CdtrAgt>
<Cdtr>
<PrTry>
<Id>2054</Id>
</PrTry>
<PFMSId>BORKH03398225</PFMSId>
<Tp/>
<Titl />
<Nm>SANGRAM JENA</Nm>
<CdtrAcct>
<Id>
<Othr>
<BBAN>3298097114</BBAN>
<SOSE />
</Othr>
</Id>
</CdtrAcct>
</Cdtr>
<TxSts>ACCP</TxSts>
<StsRsnInf>
<Rsn>
<Cd/>
<AddtlInf/>
</Rsn>
</StsRsnInf>
<AddtlInfAPBS />
</CdtTrfTxInf>
<CdtTrfTxInf>
<PmtId>
<InstrId> S9540036</InstrId>
<EndToEndId>TiroHRotH0009SFIDS2017H182054</EndToEndId>
</PmtId>
<Amt>
<CtreAmt>0</CtreAmt>
<PrvcAmt>80000</PrvcAmt>
<InstdAmt>80000</InstdAmt>
</Amt>
<CdtrAgt>
<FinInstnId>
<BICFI>STATE BANK OF INDIA</BICFI>
<BrnchId>SBIN0013573</BrnchId>
</FinInstnId>
</CdtrAgt>
<Cdtr>
<PrTry>
<Id>2054</Id>
</PrTry>
<PFMSId>BORKH08347114</PFMSId>
<Tp/>
<Titl />
<Nm>TRILOCHAN SETHY</Nm>
<CdtrAcct>
<Id>
<Othr>
<BBAN>34368165463</BBAN>
<SOSE />
</Othr>
</Id>
</CdtrAcct>
</Cdtr>
<TxSts>ACCP</TxSts>
<StsRsnInf>
<Rsn>
<Cd/>
<AddtlInf/>
</Rsn>
</StsRsnInf>
<AddtlInfAPBS />
</CdtTrfTxInf>
</PmtInf>
</CstmrCdtTrfInitn>
</DbtPaymentStatus>
